{
"meta":{"test_sets":[],"test_metrics":[],"learn_metrics":[{"best_value":"Min","name":"Logloss"}],"launch_mode":"Train","parameters":"","iteration_count":1000,"learn_sets":["learn"],"name":"experiment"},
"iterations":[
{"learn":[0.6910276141],"iteration":0,"passed_time":0.00167782758,"remaining_time":1.676149753},
{"learn":[0.6886459676],"iteration":1,"passed_time":0.002472326237,"remaining_time":1.233690792},
{"learn":[0.686075165],"iteration":2,"passed_time":0.003285574895,"remaining_time":1.091906057},
{"learn":[0.6837308435],"iteration":3,"passed_time":0.004083282381,"remaining_time":1.016737313},
{"learn":[0.6812646391],"iteration":4,"passed_time":0.004816452307,"remaining_time":0.9584740091},
{"learn":[0.6790564344],"iteration":5,"passed_time":0.005522122698,"remaining_time":0.9148316603},
{"learn":[0.6763806858],"iteration":6,"passed_time":0.006337079265,"remaining_time":0.8989599586},
{"learn":[0.6744409279],"iteration":7,"passed_time":0.006992710323,"remaining_time":0.8670960801},
{"learn":[0.6722622101],"iteration":8,"passed_time":0.007654800037,"remaining_time":0.8428785374},
{"learn":[0.6704584952],"iteration":9,"passed_time":0.008326722227,"remaining_time":0.8243455005},
{"learn":[0.6685192926],"iteration":10,"passed_time":0.008994186654,"remaining_time":0.8086591456},
{"learn":[0.6663277885],"iteration":11,"passed_time":0.009662610031,"remaining_time":0.7955548925},
{"learn":[0.664102558],"iteration":12,"passed_time":0.01031853407,"remaining_time":0.7834148562},
{"learn":[0.6617480029],"iteration":13,"passed_time":0.0111116578,"remaining_time":0.7825781853},
{"learn":[0.6598685186],"iteration":14,"passed_time":0.01191269811,"remaining_time":0.782267176},
{"learn":[0.6579593257],"iteration":15,"passed_time":0.01272994556,"remaining_time":0.7828916518},
{"learn":[0.6561024605],"iteration":16,"passed_time":0.01348878011,"remaining_time":0.7799688737},
{"learn":[0.6541360707],"iteration":17,"passed_time":0.01433181919,"remaining_time":0.7818803578},
{"learn":[0.6517192853],"iteration":18,"passed_time":0.01504628111,"remaining_time":0.7768632509},
{"learn":[0.6501047682],"iteration":19,"passed_time":0.01595756554,"remaining_time":0.7819207115},
{"learn":[0.6484931602],"iteration":20,"passed_time":0.01683635171,"remaining_time":0.7848946819},
{"learn":[0.6465987636],"iteration":21,"passed_time":0.01774688718,"remaining_time":0.7889298028},
{"learn":[0.644864144],"iteration":22,"passed_time":0.01857280116,"remaining_time":0.7889402928},
{"learn":[0.6425207593],"iteration":23,"passed_time":0.01947512807,"remaining_time":0.7919885416},
{"learn":[0.6406373188],"iteration":24,"passed_time":0.02026987672,"remaining_time":0.7905251919},
{"learn":[0.6383094298],"iteration":25,"passed_time":0.02108345836,"remaining_time":0.7898187861},
{"learn":[0.63630119],"iteration":26,"passed_time":0.0218330844,"remaining_time":0.7867996713},
{"learn":[0.6345653768],"iteration":27,"passed_time":0.02265208276,"remaining_time":0.7863508728},
{"learn":[0.6329989058],"iteration":28,"passed_time":0.02342416661,"remaining_time":0.7843057164},
{"learn":[0.6316178099],"iteration":29,"passed_time":0.02424670577,"remaining_time":0.7839768199},
{"learn":[0.630213676],"iteration":30,"passed_time":0.02492846044,"remaining_time":0.7792154246},
{"learn":[0.6284248005],"iteration":31,"passed_time":0.025874868,"remaining_time":0.7827147569},
{"learn":[0.6269963522],"iteration":32,"passed_time":0.02674557159,"remaining_time":0.7837262949},
{"learn":[0.6249508388],"iteration":33,"passed_time":0.02764668957,"remaining_time":0.7854912389},
{"learn":[0.6229464545],"iteration":34,"passed_time":0.02841469064,"remaining_time":0.7834336133},
{"learn":[0.6209059845],"iteration":35,"passed_time":0.02914927649,"remaining_time":0.7805528482},
{"learn":[0.6192700586],"iteration":36,"passed_time":0.03232335733,"remaining_time":0.8412808947},
{"learn":[0.6176001072],"iteration":37,"passed_time":0.03310664958,"remaining_time":0.8381209709},
{"learn":[0.6153794016],"iteration":38,"passed_time":0.03384615217,"remaining_time":0.8340039034},
{"learn":[0.6137696367],"iteration":39,"passed_time":0.03465410911,"remaining_time":0.8316986186},
{"learn":[0.6119516666],"iteration":40,"passed_time":0.03545494143,"remaining_time":0.8292997275},
{"learn":[0.6101470605],"iteration":41,"passed_time":0.03618090274,"remaining_time":0.8252691624},
{"learn":[0.6083427652],"iteration":42,"passed_time":0.03693057178,"remaining_time":0.8219199348},
{"learn":[0.606512849],"iteration":43,"passed_time":0.03765399123,"remaining_time":0.8181185367},
{"learn":[0.6049838858],"iteration":44,"passed_time":0.0383487462,"remaining_time":0.8138456138},
{"learn":[0.6033242912],"iteration":45,"passed_time":0.03906808287,"remaining_time":0.8102380664},
{"learn":[0.601823364],"iteration":46,"passed_time":0.04000990767,"remaining_time":0.8112647236},
{"learn":[0.6002622402],"iteration":47,"passed_time":0.0408367386,"remaining_time":0.809928649},
{"learn":[0.5984567439],"iteration":48,"passed_time":0.04157619919,"remaining_time":0.8069176619},
{"learn":[0.5967710545],"iteration":49,"passed_time":0.04311974193,"remaining_time":0.8192750967},
{"learn":[0.5951033703],"iteration":50,"passed_time":0.04383995355,"remaining_time":0.8157669788},
{"learn":[0.5935957281],"iteration":51,"passed_time":0.04457412342,"remaining_time":0.8126205577},
{"learn":[0.5919496531],"iteration":52,"passed_time":0.04536853908,"remaining_time":0.8106416323},
{"learn":[0.5901272216],"iteration":53,"passed_time":0.04613679014,"remaining_time":0.8082482124},
{"learn":[0.5887761627],"iteration":54,"passed_time":0.04709665598,"remaining_time":0.8092061801},
{"learn":[0.5876262074],"iteration":55,"passed_time":0.04781720058,"remaining_time":0.8060613812},
{"learn":[0.5865235184],"iteration":56,"passed_time":0.04854349487,"remaining_time":0.8030967661},
{"learn":[0.5846159056],"iteration":57,"passed_time":0.04942219804,"remaining_time":0.8026846648},
{"learn":[0.5832718123],"iteration":58,"passed_time":0.05018211654,"remaining_time":0.8003622316},
{"learn":[0.5819418841],"iteration":59,"passed_time":0.05110023461,"remaining_time":0.8005703422},
{"learn":[0.5797716296],"iteration":60,"passed_time":0.05193444015,"remaining_time":0.7994498246},
{"learn":[0.5783366292],"iteration":61,"passed_time":0.05278768568,"remaining_time":0.7986265995},
{"learn":[0.5772226921],"iteration":62,"passed_time":0.05357114392,"remaining_time":0.7967644739},
{"learn":[0.5757827972],"iteration":63,"passed_time":0.05432614569,"remaining_time":0.7945198807},
{"learn":[0.5742234845],"iteration":64,"passed_time":0.05514151823,"remaining_time":0.7931895315},
{"learn":[0.573216877],"iteration":65,"passed_time":0.05593439297,"remaining_time":0.7915564097},
{"learn":[0.5719217819],"iteration":66,"passed_time":0.05671722625,"remaining_time":0.7898085387},
{"learn":[0.5709498954],"iteration":67,"passed_time":0.05755855641,"remaining_time":0.7888908026},
{"learn":[0.569723921],"iteration":68,"passed_time":0.05841434481,"remaining_time":0.7881703625},
{"learn":[0.5683976878],"iteration":69,"passed_time":0.05927017419,"remaining_time":0.7874466},
{"learn":[0.5668191097],"iteration":70,"passed_time":0.06006513183,"remaining_time":0.7859226404},
{"learn":[0.5652462563],"iteration":71,"passed_time":0.06081867467,"remaining_time":0.7838851401},
{"learn":[0.5633895575],"iteration":72,"passed_time":0.06152230417,"remaining_time":0.7812489858},
{"learn":[0.5624385203],"iteration":73,"passed_time":0.06220968353,"remaining_time":0.7784617156},
{"learn":[0.5608032948],"iteration":74,"passed_time":0.06397896424,"remaining_time":0.7890738923},
{"learn":[0.5595427823],"iteration":75,"passed_time":0.0647434235,"remaining_time":0.7871437278},
{"learn":[0.5578794899],"iteration":76,"passed_time":0.06564875025,"remaining_time":0.7869324218},
{"learn":[0.5561250897],"iteration":77,"passed_time":0.06640912672,"remaining_time":0.7849899338},
{"learn":[0.5545876396],"iteration":78,"passed_time":0.06714483751,"remaining_time":0.7827898146},
{"learn":[0.5529242404],"iteration":79,"passed_time":0.06791013073,"remaining_time":0.7809665034},
{"learn":[0.5513283059],"iteration":80,"passed_time":0.06872154648,"remaining_time":0.7796926076},
{"learn":[0.5498897571],"iteration":81,"passed_time":0.06961854068,"remaining_time":0.7793880529},
{"learn":[0.5484879638],"iteration":82,"passed_time":0.07066044415,"remaining_time":0.7806702082},
{"learn":[0.5471889375],"iteration":83,"passed_time":0.07155023073,"remaining_time":0.7802382303},
{"learn":[0.5461745065],"iteration":84,"passed_time":0.07230744037,"remaining_time":0.7783683287},
{"learn":[0.5451677792],"iteration":85,"passed_time":0.07309031565,"remaining_time":0.7767970756},
{"learn":[0.5437365331],"iteration":86,"passed_time":0.07390718911,"remaining_time":0.7756007317},
{"learn":[0.5428510899],"iteration":87,"passed_time":0.07469802197,"remaining_time":0.7741431367},
{"learn":[0.5414952334],"iteration":88,"passed_time":0.0755529354,"remaining_time":0.7733564512},
{"learn":[0.5402059222],"iteration":89,"passed_time":0.07629364593,"remaining_time":0.771413531},
{"learn":[0.5390765319],"iteration":90,"passed_time":0.07700414906,"remaining_time":0.7691952912},
{"learn":[0.5380762436],"iteration":91,"passed_time":0.07796351493,"remaining_time":0.7694659952},
{"learn":[0.5367215218],"iteration":92,"passed_time":0.07871185005,"remaining_time":0.767652129},
{"learn":[0.5355549598],"iteration":93,"passed_time":0.07954034789,"remaining_time":0.7666335659},
{"learn":[0.534074382],"iteration":94,"passed_time":0.08041130148,"remaining_time":0.7660234509},
{"learn":[0.5329111528],"iteration":95,"passed_time":0.08119096792,"remaining_time":0.7645482813},
{"learn":[0.5318406902],"iteration":96,"passed_time":0.08197913392,"remaining_time":0.7631665766},
{"learn":[0.5308872171],"iteration":97,"passed_time":0.08275971732,"remaining_time":0.7617271941},
{"learn":[0.5297164151],"iteration":98,"passed_time":0.08355825776,"remaining_time":0.7604645479},
{"learn":[0.5282222404],"iteration":99,"passed_time":0.08430750983,"remaining_time":0.7587675885},
{"learn":[0.5268777965],"iteration":100,"passed_time":0.08574589117,"remaining_time":0.7632233283},
{"learn":[0.5257340592],"iteration":101,"passed_time":0.08660638731,"remaining_time":0.7624758412},
{"learn":[0.5246500323],"iteration":102,"passed_time":0.08756583618,"remaining_time":0.7625879131},
{"learn":[0.5233891262],"iteration":103,"passed_time":0.0883290455,"remaining_time":0.7609886997},
{"learn":[0.5224196234],"iteration":104,"passed_time":0.08918070811,"remaining_time":0.7601593691},
{"learn":[0.5210758463],"iteration":105,"passed_time":0.09006611992,"remaining_time":0.7596142567},
{"learn":[0.5198813379],"iteration":106,"passed_time":0.09085520287,"remaining_time":0.7582588426},
{"learn":[0.519026896],"iteration":107,"passed_time":0.09162474486,"remaining_time":0.7567525223},
{"learn":[0.5176950705],"iteration":108,"passed_time":0.09237287198,"remaining_time":0.7550846692},
{"learn":[0.5166673625],"iteration":109,"passed_time":0.09317107944,"remaining_time":0.7538387337},
{"learn":[0.5159472111],"iteration":110,"passed_time":0.09391903958,"remaining_time":0.7521984341},
{"learn":[0.5151940007],"iteration":111,"passed_time":0.09479157608,"remaining_time":0.7515617818},
{"learn":[0.5141322328],"iteration":112,"passed_time":0.09560261586,"remaining_time":0.7504382324},
{"learn":[0.5130699714],"iteration":113,"passed_time":0.096312828,"remaining_time":0.7485365405},
{"learn":[0.5119715062],"iteration":114,"passed_time":0.09727111093,"remaining_time":0.7485646363},
{"learn":[0.5109118974],"iteration":115,"passed_time":0.09803827805,"remaining_time":0.7471192913},
{"learn":[0.5099235175],"iteration":116,"passed_time":0.09881865346,"remaining_time":0.7457852222},
{"learn":[0.5089786151],"iteration":117,"passed_time":0.09960386161,"remaining_time":0.7444966605},
{"learn":[0.5079394316],"iteration":118,"passed_time":0.1003791533,"remaining_time":0.7431431433},
{"learn":[0.5067641354],"iteration":119,"passed_time":0.1012258582,"remaining_time":0.7423229599},
{"learn":[0.5053116459],"iteration":120,"passed_time":0.1020824375,"remaining_time":0.7415740709},
{"learn":[0.5042926491],"iteration":121,"passed_time":0.1028708125,"remaining_time":0.7403325686},
{"learn":[0.503373463],"iteration":122,"passed_time":0.1038392609,"remaining_time":0.7403823723},
{"learn":[0.5022993159],"iteration":123,"passed_time":0.1046273439,"remaining_time":0.7391415584},
{"learn":[0.5012634666],"iteration":124,"passed_time":0.1054800894,"remaining_time":0.738360626},
{"learn":[0.4998851219],"iteration":125,"passed_time":0.1062151753,"remaining_time":0.7367624062},
{"learn":[0.4986077859],"iteration":126,"passed_time":0.1069762597,"remaining_time":0.7353564938},
{"learn":[0.4978629525],"iteration":127,"passed_time":0.1081409476,"remaining_time":0.7367102057},
{"learn":[0.4964345827],"iteration":128,"passed_time":0.1089921103,"remaining_time":0.7359079693},
{"learn":[0.4949686639],"iteration":129,"passed_time":0.1097883178,"remaining_time":0.7347372039},
{"learn":[0.4940751818],"iteration":130,"passed_time":0.1105013628,"remaining_time":0.7330204908},
{"learn":[0.4928087432],"iteration":131,"passed_time":0.111324528,"remaining_time":0.7320431081},
{"learn":[0.4919991524],"iteration":132,"passed_time":0.1121420264,"remaining_time":0.7310311043},
{"learn":[0.4909603278],"iteration":133,"passed_time":0.1131098088,"remaining_time":0.730993242},
{"learn":[0.4901510651],"iteration":134,"passed_time":0.1138929751,"remaining_time":0.7297586921},
{"learn":[0.4888666079],"iteration":135,"passed_time":0.115002166,"remaining_time":0.7306019955},
{"learn":[0.4875607347],"iteration":136,"passed_time":0.1158607032,"remaining_time":0.7298378603},
{"learn":[0.4867060976],"iteration":137,"passed_time":0.1167596553,"remaining_time":0.7293248033},
{"learn":[0.4858281922],"iteration":138,"passed_time":0.1175790276,"remaining_time":0.7283132574},
{"learn":[0.4844360857],"iteration":139,"passed_time":0.1183729433,"remaining_time":0.7271480803},
{"learn":[0.4836692944],"iteration":140,"passed_time":0.1191724417,"remaining_time":0.7260221803},
{"learn":[0.4830970847],"iteration":141,"passed_time":0.119954442,"remaining_time":0.7247951497},
{"learn":[0.4823135347],"iteration":142,"passed_time":0.1208467285,"remaining_time":0.7242352888},
{"learn":[0.4814667255],"iteration":143,"passed_time":0.1218090102,"remaining_time":0.7240868939},
{"learn":[0.4807108741],"iteration":144,"passed_time":0.122637841,"remaining_time":0.7231403729},
{"learn":[0.4800026225],"iteration":145,"passed_time":0.1235475005,"remaining_time":0.7226682565},
{"learn":[0.4791538797],"iteration":146,"passed_time":0.1242684211,"remaining_time":0.7210949878},
{"learn":[0.4783221518],"iteration":147,"passed_time":0.1250465046,"remaining_time":0.7198623105},
{"learn":[0.4773952692],"iteration":148,"passed_time":0.1258827931,"remaining_time":0.7189681671},
{"learn":[0.4768871777],"iteration":149,"passed_time":0.1266583347,"remaining_time":0.7177305635},
{"learn":[0.476018758],"iteration":150,"passed_time":0.1274681246,"remaining_time":0.7166916409},
{"learn":[0.4748247219],"iteration":151,"passed_time":0.1282872469,"remaining_time":0.7157077986},
{"learn":[0.4737375382],"iteration":152,"passed_time":0.1291252853,"remaining_time":0.7148308276},
{"learn":[0.4726532032],"iteration":153,"passed_time":0.1298922024,"remaining_time":0.7135636573},
{"learn":[0.471420684],"iteration":154,"passed_time":0.1306843262,"remaining_time":0.7124403588},
{"learn":[0.4702336057],"iteration":155,"passed_time":0.1315453633,"remaining_time":0.711694145},
{"learn":[0.4693524253],"iteration":156,"passed_time":0.1324458573,"remaining_time":0.7111583293},
{"learn":[0.4685747047],"iteration":157,"passed_time":0.1332440228,"remaining_time":0.710072577},
{"learn":[0.4679490258],"iteration":158,"passed_time":0.1341118105,"remaining_time":0.7093586958},
{"learn":[0.4672897725],"iteration":159,"passed_time":0.1349394334,"remaining_time":0.7084320253},
{"learn":[0.4664099464],"iteration":160,"passed_time":0.1358054702,"remaining_time":0.7077067673},
{"learn":[0.4658679865],"iteration":161,"passed_time":0.1366691322,"remaining_time":0.7069674864},
{"learn":[0.4648075708],"iteration":162,"passed_time":0.13746084,"remaining_time":0.7058571969},
{"learn":[0.464077606],"iteration":163,"passed_time":0.1382962955,"remaining_time":0.704973799},
{"learn":[0.4631911646],"iteration":164,"passed_time":0.1390721711,"remaining_time":0.7037894722},
{"learn":[0.4624887016],"iteration":165,"passed_time":0.1398386303,"remaining_time":0.702562757},
{"learn":[0.4613696165],"iteration":166,"passed_time":0.1406760027,"remaining_time":0.7016952708},
{"learn":[0.4605943214],"iteration":167,"passed_time":0.1414808348,"remaining_time":0.7006669913},
{"learn":[0.4598313407],"iteration":168,"passed_time":0.1424168679,"remaining_time":0.7002864924},
{"learn":[0.4593214635],"iteration":169,"passed_time":0.1432661976,"remaining_time":0.6994761413},
{"learn":[0.4587126641],"iteration":170,"passed_time":0.1439747439,"remaining_time":0.6979828226},
{"learn":[0.4582001],"iteration":171,"passed_time":0.1448737369,"remaining_time":0.6974154314},
{"learn":[0.4574915207],"iteration":172,"passed_time":0.1456080318,"remaining_time":0.696056892},
{"learn":[0.4570323597],"iteration":173,"passed_time":0.1462883286,"remaining_time":0.6944491919},
{"learn":[0.4563285318],"iteration":174,"passed_time":0.1472584019,"remaining_time":0.6942181802},
{"learn":[0.4555694186],"iteration":175,"passed_time":0.1480956072,"remaining_time":0.6933567066},
{"learn":[0.4548397395],"iteration":176,"passed_time":0.148889023,"remaining_time":0.6922918977},
{"learn":[0.4540089723],"iteration":177,"passed_time":0.1496903962,"remaining_time":0.691266886},
{"learn":[0.4534771706],"iteration":178,"passed_time":0.1503740258,"remaining_time":0.6897043307},
{"learn":[0.4526815745],"iteration":179,"passed_time":0.1512826024,"remaining_time":0.6891762998},
{"learn":[0.451736786],"iteration":180,"passed_time":0.1520872675,"remaining_time":0.6881738789},
{"learn":[0.4506734],"iteration":181,"passed_time":0.1530010098,"remaining_time":0.6876638792},
{"learn":[0.4501016332],"iteration":182,"passed_time":0.1537321798,"remaining_time":0.6863343767},
{"learn":[0.4495657903],"iteration":183,"passed_time":0.1543213984,"remaining_time":0.6843818539},
{"learn":[0.4489465743],"iteration":184,"passed_time":0.1550151535,"remaining_time":0.682904595},
{"learn":[0.4481483723],"iteration":185,"passed_time":0.1557338652,"remaining_time":0.6815449798},
{"learn":[0.4475517002],"iteration":186,"passed_time":0.1565199063,"remaining_time":0.6804849401},
{"learn":[0.4471127774],"iteration":187,"passed_time":0.1573491951,"remaining_time":0.6796146085},
{"learn":[0.4463416278],"iteration":188,"passed_time":0.158194067,"remaining_time":0.6788115787},
{"learn":[0.445393045],"iteration":189,"passed_time":0.1591291832,"remaining_time":0.6783928337},
{"learn":[0.4447729309],"iteration":190,"passed_time":0.1600014697,"remaining_time":0.6777025602},
{"learn":[0.4439100445],"iteration":191,"passed_time":0.1608145934,"remaining_time":0.6767614138},
{"learn":[0.4433041579],"iteration":192,"passed_time":0.1618667873,"remaining_time":0.6768212298},
{"learn":[0.4428658391],"iteration":193,"passed_time":0.1626403291,"remaining_time":0.6757118827},
{"learn":[0.4423701252],"iteration":194,"passed_time":0.1634210375,"remaining_time":0.6746355649},
{"learn":[0.4419189328],"iteration":195,"passed_time":0.1642599928,"remaining_time":0.6738011948},
{"learn":[0.4410077446],"iteration":196,"passed_time":0.1649965375,"remaining_time":0.6725493381},
{"learn":[0.440323843],"iteration":197,"passed_time":0.1657703303,"remaining_time":0.67145356},
{"learn":[0.439353265],"iteration":198,"passed_time":0.1672930411,"remaining_time":0.6733755072},
{"learn":[0.4386671182],"iteration":199,"passed_time":0.1681659946,"remaining_time":0.6726639783},
{"learn":[0.438090469],"iteration":200,"passed_time":0.1690061578,"remaining_time":0.671820498},
{"learn":[0.4375061565],"iteration":201,"passed_time":0.1699090677,"remaining_time":0.6712249308},
{"learn":[0.4365807776],"iteration":202,"passed_time":0.1706937759,"remaining_time":0.6701622629},
{"learn":[0.4359077633],"iteration":203,"passed_time":0.1714879415,"remaining_time":0.6691392229},
{"learn":[0.435392744],"iteration":204,"passed_time":0.1723098137,"remaining_time":0.668225863},
{"learn":[0.4345540234],"iteration":205,"passed_time":0.1731635602,"remaining_time":0.6674362468},
{"learn":[0.433712724],"iteration":206,"passed_time":0.174030514,"remaining_time":0.6666966069},
{"learn":[0.432888133],"iteration":207,"passed_time":0.1748396789,"remaining_time":0.6657357005},
{"learn":[0.4322204559],"iteration":208,"passed_time":0.1756305538,"remaining_time":0.6647070241},
{"learn":[0.4316448445],"iteration":209,"passed_time":0.1764734668,"remaining_time":0.6638763753},
{"learn":[0.4309920694],"iteration":210,"passed_time":0.1773074634,"remaining_time":0.6630122683},
{"learn":[0.4300917871],"iteration":211,"passed_time":0.178197374,"remaining_time":0.6623562768},
{"learn":[0.4296290166],"iteration":212,"passed_time":0.1790064138,"remaining_time":0.661399285},
{"learn":[0.4284761862],"iteration":213,"passed_time":0.1798520768,"remaining_time":0.6605781885},
{"learn":[0.4277347597],"iteration":214,"passed_time":0.1806388258,"remaining_time":0.6595417595},
{"learn":[0.4267946195],"iteration":215,"passed_time":0.1816320229,"remaining_time":0.6592569721},
{"learn":[0.4260965146],"iteration":216,"passed_time":0.1823905665,"remaining_time":0.6581189565},
{"learn":[0.4255461563],"iteration":217,"passed_time":0.1831472342,"remaining_time":0.6569776932},
{"learn":[0.424882286],"iteration":218,"passed_time":0.1840376447,"remaining_time":0.6563168973},
{"learn":[0.4242530577],"iteration":219,"passed_time":0.184932764,"remaining_time":0.6556707087},
{"learn":[0.4235747207],"iteration":220,"passed_time":0.185645309,"remaining_time":0.6543787137},
{"learn":[0.423047135],"iteration":221,"passed_time":0.1864811395,"remaining_time":0.6535239933},
{"learn":[0.4225504586],"iteration":222,"passed_time":0.1873090114,"remaining_time":0.6526417122},
{"learn":[0.4220752215],"iteration":223,"passed_time":0.1883829961,"remaining_time":0.6526125223},
{"learn":[0.4215386202],"iteration":224,"passed_time":0.1893454448,"remaining_time":0.6521898655},
{"learn":[0.4206032885],"iteration":225,"passed_time":0.1902264399,"remaining_time":0.6514834711},
{"learn":[0.4200298076],"iteration":226,"passed_time":0.1910911018,"remaining_time":0.6507199193},
{"learn":[0.4194786518],"iteration":227,"passed_time":0.1918736021,"remaining_time":0.6496772843},
{"learn":[0.418799075],"iteration":228,"passed_time":0.1926973912,"remaining_time":0.6487759328},
{"learn":[0.4182825483],"iteration":229,"passed_time":0.1935461789,"remaining_time":0.6479589469},
{"learn":[0.4173584168],"iteration":230,"passed_time":0.1943728849,"remaining_time":0.6470681752},
{"learn":[0.4167750387],"iteration":231,"passed_time":0.1952040486,"remaining_time":0.6461927126},
{"learn":[0.4163525387],"iteration":232,"passed_time":0.196041004,"remaining_time":0.6453366955},
{"learn":[0.4158119298],"iteration":233,"passed_time":0.1968134218,"remaining_time":0.6442695774},
{"learn":[0.415255003],"iteration":234,"passed_time":0.1975810889,"remaining_time":0.6431895022},
{"learn":[0.4143744434],"iteration":235,"passed_time":0.1984278348,"remaining_time":0.6423680753},
{"learn":[0.4138911001],"iteration":236,"passed_time":0.1993712015,"remaining_time":0.6418574968},
{"learn":[0.4135069251],"iteration":237,"passed_time":0.2001626593,"remaining_time":0.6408569177},
{"learn":[0.4130077619],"iteration":238,"passed_time":0.2009103695,"remaining_time":0.6397187915},
{"learn":[0.4123652159],"iteration":239,"passed_time":0.2017412832,"remaining_time":0.6388473968},
{"learn":[0.4117587422],"iteration":240,"passed_time":0.2025955297,"remaining_time":0.6380498216},
{"learn":[0.4112315168],"iteration":241,"passed_time":0.203451734,"remaining_time":0.6372579107},
{"learn":[0.4106875076],"iteration":242,"passed_time":0.2043087304,"remaining_time":0.6364679378},
{"learn":[0.410356039],"iteration":243,"passed_time":0.205122521,"remaining_time":0.6355435486},
{"learn":[0.4099827407],"iteration":244,"passed_time":0.2060759702,"remaining_time":0.6350504387},
{"learn":[0.4095058633],"iteration":245,"passed_time":0.2069709635,"remaining_time":0.6343744165},
{"learn":[0.4089209664],"iteration":246,"passed_time":0.2078593741,"remaining_time":0.6336765535},
{"learn":[0.4082937111],"iteration":247,"passed_time":0.2087079959,"remaining_time":0.6328565037},
{"learn":[0.4079013827],"iteration":248,"passed_time":0.2095287022,"remaining_time":0.6319520294},
{"learn":[0.4075402765],"iteration":249,"passed_time":0.2103745731,"remaining_time":0.6311237192},
{"learn":[0.4069868388],"iteration":250,"passed_time":0.211239235,"remaining_time":0.6303513427},
{"learn":[0.4066424101],"iteration":251,"passed_time":0.2120345676,"remaining_time":0.6293724467},
{"learn":[0.40589391],"iteration":252,"passed_time":0.2129048542,"remaining_time":0.6286163087},
{"learn":[0.4052155825],"iteration":253,"passed_time":0.213715102,"remaining_time":0.6276829375},
{"learn":[0.4044011272],"iteration":254,"passed_time":0.214617096,"remaining_time":0.6270185745},
{"learn":[0.4035662302],"iteration":255,"passed_time":0.2154783001,"remaining_time":0.6262338096},
{"learn":[0.402536465],"iteration":256,"passed_time":0.2164857044,"remaining_time":0.625871122},
{"learn":[0.4020312252],"iteration":257,"passed_time":0.2173148272,"remaining_time":0.6249907046},
{"learn":[0.4015773386],"iteration":258,"passed_time":0.2180945776,"remaining_time":0.6239694287},
{"learn":[0.4011684176],"iteration":259,"passed_time":0.2188613288,"remaining_time":0.6229130127},
{"learn":[0.4004726209],"iteration":260,"passed_time":0.2197240738,"remaining_time":0.6221306151},
{"learn":[0.4001827656],"iteration":261,"passed_time":0.2206408999,"remaining_time":0.6214999395},
{"learn":[0.3996878502],"iteration":262,"passed_time":0.2215567261,"remaining_time":0.6208642858},
{"learn":[0.3990337885],"iteration":263,"passed_time":0.2224354293,"remaining_time":0.620123015},
{"learn":[0.3982930729],"iteration":264,"passed_time":0.223360047,"remaining_time":0.6195080549},
{"learn":[0.3978086478],"iteration":265,"passed_time":0.2242454158,"remaining_time":0.6187824632},
{"learn":[0.3972819879],"iteration":266,"passed_time":0.2250420824,"remaining_time":0.6178121587},
{"learn":[0.3965893376],"iteration":267,"passed_time":0.2259687,"remaining_time":0.617198091},
{"learn":[0.396258881],"iteration":268,"passed_time":0.2268046134,"remaining_time":0.6163352135},
{"learn":[0.3956137021],"iteration":269,"passed_time":0.2276133623,"remaining_time":0.6153990908},
{"learn":[0.3952869221],"iteration":270,"passed_time":0.2284786492,"remaining_time":0.6146159974},
{"learn":[0.3947075176],"iteration":271,"passed_time":0.2291836536,"remaining_time":0.6134033083},
{"learn":[0.3943815245],"iteration":272,"passed_time":0.2299663619,"remaining_time":0.6124012642},
{"learn":[0.393849165],"iteration":273,"passed_time":0.2307585277,"remaining_time":0.61142588},
{"learn":[0.3935177464],"iteration":274,"passed_time":0.231560068,"remaining_time":0.6104765429},
{"learn":[0.3931722006],"iteration":275,"passed_time":0.2323619833,"remaining_time":0.6095292604},
{"learn":[0.392719036],"iteration":276,"passed_time":0.2331508162,"remaining_time":0.6085488813},
{"learn":[0.3923547647],"iteration":277,"passed_time":0.2339906465,"remaining_time":0.6077023264},
{"learn":[0.3916842434],"iteration":278,"passed_time":0.2348034361,"remaining_time":0.6067859407},
{"learn":[0.391073405],"iteration":279,"passed_time":0.2356702229,"remaining_time":0.6060091447},
{"learn":[0.3905404976],"iteration":280,"passed_time":0.2365586336,"remaining_time":0.6052870376},
{"learn":[0.3899478968],"iteration":281,"passed_time":0.2373368841,"remaining_time":0.6042832723},
{"learn":[0.3892431995],"iteration":282,"passed_time":0.2380460963,"remaining_time":0.6031061875},
{"learn":[0.3888239175],"iteration":283,"passed_time":0.2387874318,"remaining_time":0.6020133844},
{"learn":[0.388350403],"iteration":284,"passed_time":0.2395960137,"remaining_time":0.6010917537},
{"learn":[0.3877536753],"iteration":285,"passed_time":0.2412454678,"remaining_time":0.6022701539},
{"learn":[0.3871702111],"iteration":286,"passed_time":0.2419865113,"remaining_time":0.6011720647},
{"learn":[0.3866650342],"iteration":287,"passed_time":0.2428465065,"remaining_time":0.6003705299},
{"learn":[0.3862623491],"iteration":288,"passed_time":0.2436115907,"remaining_time":0.59933509},
{"learn":[0.3856941115],"iteration":289,"passed_time":0.2444734618,"remaining_time":0.5985384754},
{"learn":[0.3850930385],"iteration":290,"passed_time":0.2452865024,"remaining_time":0.5976224407},
{"learn":[0.3845480795],"iteration":291,"passed_time":0.2460660859,"remaining_time":0.5966259891},
{"learn":[0.3839540187],"iteration":292,"passed_time":0.2468491692,"remaining_time":0.5956394628},
{"learn":[0.383465602],"iteration":293,"passed_time":0.247547298,"remaining_time":0.5944503141},
{"learn":[0.3827687591],"iteration":294,"passed_time":0.2484310009,"remaining_time":0.5937079851},
{"learn":[0.3825270793],"iteration":295,"passed_time":0.2492225007,"remaining_time":0.592745407},
{"learn":[0.3818454791],"iteration":296,"passed_time":0.2500634969,"remaining_time":0.591901139},
{"learn":[0.38167286],"iteration":297,"passed_time":0.2509159514,"remaining_time":0.5910838856},
{"learn":[0.3812344628],"iteration":298,"passed_time":0.2517829462,"remaining_time":0.590300486},
{"learn":[0.3808736906],"iteration":299,"passed_time":0.2525847785,"remaining_time":0.5893644831},
{"learn":[0.3803567085],"iteration":300,"passed_time":0.2535251444,"remaining_time":0.5887510828},
{"learn":[0.379702003],"iteration":301,"passed_time":0.2543618918,"remaining_time":0.587896028},
{"learn":[0.3792971289],"iteration":302,"passed_time":0.2552295115,"remaining_time":0.5871121107},
{"learn":[0.378607574],"iteration":303,"passed_time":0.2561051739,"remaining_time":0.586346056},
{"learn":[0.3782635422],"iteration":304,"passed_time":0.2570294576,"remaining_time":0.5856900755},
{"learn":[0.377851085],"iteration":305,"passed_time":0.2578979943,"remaining_time":0.5849059087},
{"learn":[0.3774710905],"iteration":306,"passed_time":0.2588547773,"remaining_time":0.5843203931},
{"learn":[0.3767590763],"iteration":307,"passed_time":0.2597156894,"remaining_time":0.5835170685},
{"learn":[0.3764276526],"iteration":308,"passed_time":0.260531729,"remaining_time":0.5826130249},
{"learn":[0.3758745288],"iteration":309,"passed_time":0.2613665175,"remaining_time":0.5817512808},
{"learn":[0.3754552342],"iteration":310,"passed_time":0.2621598502,"remaining_time":0.5807978674},
{"learn":[0.3748609964],"iteration":311,"passed_time":0.2629105182,"remaining_time":0.5797513991},
{"learn":[0.3743711803],"iteration":312,"passed_time":0.2638859662,"remaining_time":0.5792001878},
{"learn":[0.3738495889],"iteration":313,"passed_time":0.2646338013,"remaining_time":0.5781490055},
{"learn":[0.3731612995],"iteration":314,"passed_time":0.2654636731,"remaining_time":0.5772781463},
{"learn":[0.3727868722],"iteration":315,"passed_time":0.2661334714,"remaining_time":0.5760610584},
{"learn":[0.3724112455],"iteration":316,"passed_time":0.2668680983,"remaining_time":0.5749871013},
{"learn":[0.371944274],"iteration":317,"passed_time":0.2676687226,"remaining_time":0.5740568201},
{"learn":[0.3717825345],"iteration":318,"passed_time":0.2683881432,"remaining_time":0.5729539986},
{"learn":[0.3711992705],"iteration":319,"passed_time":0.2692140152,"remaining_time":0.5720797824},
{"learn":[0.3707432408],"iteration":320,"passed_time":0.2701065927,"remaining_time":0.571346967},
{"learn":[0.3701460311],"iteration":321,"passed_time":0.270925924,"remaining_time":0.5704589331},
{"learn":[0.369798496],"iteration":322,"passed_time":0.2721658169,"remaining_time":0.5704528113},
{"learn":[0.3690970259],"iteration":323,"passed_time":0.2729244435,"remaining_time":0.56943495},
{"learn":[0.3686374337],"iteration":324,"passed_time":0.2738173119,"remaining_time":0.5686974939},
{"learn":[0.3682196763],"iteration":325,"passed_time":0.2747126392,"remaining_time":0.5679641681},
{"learn":[0.3676507899],"iteration":326,"passed_time":0.2755083888,"remaining_time":0.5670249102},
{"learn":[0.36733092],"iteration":327,"passed_time":0.2763782594,"remaining_time":0.5662383851},
{"learn":[0.3669512446],"iteration":328,"passed_time":0.2771655515,"remaining_time":0.5652829332},
{"learn":[0.366524493],"iteration":329,"passed_time":0.2780482544,"remaining_time":0.5645222135},
{"learn":[0.3661884751],"iteration":330,"passed_time":0.2789409568,"remaining_time":0.5637809671},
{"learn":[0.3658116636],"iteration":331,"passed_time":0.2798089946,"remaining_time":0.5629891818},
{"learn":[0.3651888374],"iteration":332,"passed_time":0.280738611,"remaining_time":0.5623202809},
{"learn":[0.3646648832],"iteration":333,"passed_time":0.2816254388,"remaining_time":0.5615644977},
{"learn":[0.3643040858],"iteration":334,"passed_time":0.282539765,"remaining_time":0.5608625186},
{"learn":[0.363867529],"iteration":335,"passed_time":0.2834509255,"remaining_time":0.5601530194},
{"learn":[0.3635096233],"iteration":336,"passed_time":0.284472412,"remaining_time":0.5596593744},
{"learn":[0.3628973349],"iteration":337,"passed_time":0.2853186169,"remaining_time":0.558819303},
{"learn":[0.3623599594],"iteration":338,"passed_time":0.2860707019,"remaining_time":0.5577956753},
{"learn":[0.3619989524],"iteration":339,"passed_time":0.2868484524,"remaining_time":0.5568234664},
{"learn":[0.3615977514],"iteration":340,"passed_time":0.2876549094,"remaining_time":0.5559078748},
{"learn":[0.3610280172],"iteration":341,"passed_time":0.2884843232,"remaining_time":0.5550370897},
{"learn":[0.3605005805],"iteration":342,"passed_time":0.2892586989,"remaining_time":0.5540611231},
{"learn":[0.3600239506],"iteration":343,"passed_time":0.2900915296,"remaining_time":0.5531978006},
{"learn":[0.3595440999],"iteration":344,"passed_time":0.2909573584,"remaining_time":0.5523973037},
{"learn":[0.3591933461],"iteration":345,"passed_time":0.2917512321,"remaining_time":0.5514604214},
{"learn":[0.3586042878],"iteration":346,"passed_time":0.2924817352,"remaining_time":0.5504051097},
{"learn":[0.3582685292],"iteration":347,"passed_time":0.2932619856,"remaining_time":0.5494448696},
{"learn":[0.3579965725],"iteration":348,"passed_time":0.294098149,"remaining_time":0.5485899571},
{"learn":[0.3576624475],"iteration":349,"passed_time":0.2949702276,"remaining_time":0.5478018512},
{"learn":[0.3572752938],"iteration":350,"passed_time":0.2956229428,"remaining_time":0.5466076634},
{"learn":[0.3569646532],"iteration":351,"passed_time":0.296462982,"remaining_time":0.5457613987},
{"learn":[0.356536817],"iteration":352,"passed_time":0.2972344409,"remaining_time":0.544789471},
{"learn":[0.3562490619],"iteration":353,"passed_time":0.2980531892,"remaining_time":0.5439049725},
{"learn":[0.3558902764],"iteration":354,"passed_time":0.2990692191,"remaining_time":0.5433792854},
{"learn":[0.3555166956],"iteration":355,"passed_time":0.2999685882,"remaining_time":0.5426398056},
{"learn":[0.3551923433],"iteration":356,"passed_time":0.3009261201,"remaining_time":0.5420041884},
{"learn":[0.3547870076],"iteration":357,"passed_time":0.3017382019,"remaining_time":0.5411059374},
{"learn":[0.354469327],"iteration":358,"passed_time":0.3025460338,"remaining_time":0.5402005785},
{"learn":[0.3541318408],"iteration":359,"passed_time":0.3034487767,"remaining_time":0.5394644919},
{"learn":[0.3539513597],"iteration":360,"passed_time":0.304418808,"remaining_time":0.5388465881},
{"learn":[0.3537756534],"iteration":361,"passed_time":0.3052944703,"remaining_time":0.5380604201},
{"learn":[0.3534799137],"iteration":362,"passed_time":0.3060680541,"remaining_time":0.5370946294},
{"learn":[0.3531196309],"iteration":363,"passed_time":0.3069949217,"remaining_time":0.5363977203},
{"learn":[0.3529088015],"iteration":364,"passed_time":0.3078865412,"remaining_time":0.5356382292},
{"learn":[0.3523480623],"iteration":365,"passed_time":0.3088180755,"remaining_time":0.5349471582},
{"learn":[0.3522093871],"iteration":366,"passed_time":0.3103241613,"remaining_time":0.5352457604},
{"learn":[0.3515211961],"iteration":367,"passed_time":0.3110922453,"remaining_time":0.534267117},
{"learn":[0.3511030362],"iteration":368,"passed_time":0.3119722814,"remaining_time":0.5334810558},
{"learn":[0.3506259905],"iteration":369,"passed_time":0.3127667391,"remaining_time":0.532548772},
{"learn":[0.350299699],"iteration":370,"passed_time":0.3135671964,"remaining_time":0.5316274031},
{"learn":[0.3497504315],"iteration":371,"passed_time":0.3144246927,"remaining_time":0.5308029759},
{"learn":[0.3490373572],"iteration":372,"passed_time":0.3151658202,"remaining_time":0.5297827595},
{"learn":[0.3487947659],"iteration":373,"passed_time":0.3159281956,"remaining_time":0.5287996001},
{"learn":[0.3482895416],"iteration":374,"passed_time":0.3166615725,"remaining_time":0.5277692875},
{"learn":[0.3480718248],"iteration":375,"passed_time":0.3174552802,"remaining_time":0.5268406778},
{"learn":[0.3477815275],"iteration":376,"passed_time":0.318434394,"remaining_time":0.526219171},
{"learn":[0.3474002351],"iteration":377,"passed_time":0.3198159044,"remaining_time":0.5262579168},
{"learn":[0.3469266611],"iteration":378,"passed_time":0.3206693169,"remaining_time":0.5254238676},
{"learn":[0.346538375],"iteration":379,"passed_time":0.3213851538,"remaining_time":0.5243652509},
{"learn":[0.3459833193],"iteration":380,"passed_time":0.3221527789,"remaining_time":0.5233925725},
{"learn":[0.3455446082],"iteration":381,"passed_time":0.3230350238,"remaining_time":0.5226063998},
{"learn":[0.3451601828],"iteration":382,"passed_time":0.3239277673,"remaining_time":0.5218366381},
{"learn":[0.3446700081],"iteration":383,"passed_time":0.3248682171,"remaining_time":0.521142765},
{"learn":[0.3441349465],"iteration":384,"passed_time":0.3257380038,"remaining_time":0.5203347333},
{"learn":[0.3435848448],"iteration":385,"passed_time":0.3266544549,"remaining_time":0.5196006097},
{"learn":[0.3430691367],"iteration":386,"passed_time":0.3274265808,"remaining_time":0.5186369355},
{"learn":[0.3427701751],"iteration":387,"passed_time":0.3282829511,"remaining_time":0.5178071291},
{"learn":[0.3425347702],"iteration":388,"passed_time":0.3291914027,"remaining_time":0.5170589899},
{"learn":[0.3422175992],"iteration":389,"passed_time":0.329917823,"remaining_time":0.5160253129},
{"learn":[0.3418924067],"iteration":390,"passed_time":0.3306399515,"remaining_time":0.514986523},
{"learn":[0.3415696894],"iteration":391,"passed_time":0.3314726992,"remaining_time":0.5141209211},
{"learn":[0.3412446912],"iteration":392,"passed_time":0.3322755724,"remaining_time":0.5132093446},
{"learn":[0.3409519457],"iteration":393,"passed_time":0.3331495258,"remaining_time":0.5124076463},
{"learn":[0.3407054532],"iteration":394,"passed_time":0.3340058551,"remaining_time":0.5115785883},
{"learn":[0.3404062669],"iteration":395,"passed_time":0.3349068071,"remaining_time":0.5108174533},
{"learn":[0.3402473743],"iteration":396,"passed_time":0.3357298883,"remaining_time":0.5099373366},
{"learn":[0.3398961553],"iteration":397,"passed_time":0.3365135545,"remaining_time":0.508997889},
{"learn":[0.3394430779],"iteration":398,"passed_time":0.3372878052,"remaining_time":0.50804504},
{"learn":[0.3391242453],"iteration":399,"passed_time":0.3381211358,"remaining_time":0.5071817037},
{"learn":[0.3387039879],"iteration":400,"passed_time":0.3389728404,"remaining_time":0.5063459636},
{"learn":[0.3381588002],"iteration":401,"passed_time":0.3398275449,"remaining_time":0.5055146066},
{"learn":[0.3375277819],"iteration":402,"passed_time":0.3407224142,"remaining_time":0.5047426334},
{"learn":[0.337171063],"iteration":403,"passed_time":0.3415488701,"remaining_time":0.5038691253},
{"learn":[0.3366202611],"iteration":404,"passed_time":0.342396116,"remaining_time":0.5030263926},
{"learn":[0.3362280177],"iteration":405,"passed_time":0.3432834027,"remaining_time":0.5022422197},
{"learn":[0.3355088962],"iteration":406,"passed_time":0.3441134415,"remaining_time":0.5013741297},
{"learn":[0.3349651176],"iteration":407,"passed_time":0.3450187272,"remaining_time":0.5006154081},
{"learn":[0.3346616802],"iteration":408,"passed_time":0.3459010142,"remaining_time":0.4998227369},
{"learn":[0.3341137111],"iteration":409,"passed_time":0.3467946326,"remaining_time":0.4990459347},
{"learn":[0.3337003281],"iteration":410,"passed_time":0.3483443,"remaining_time":0.4992087413},
{"learn":[0.3333963761],"iteration":411,"passed_time":0.3492596672,"remaining_time":0.4984579716},
{"learn":[0.3331116471],"iteration":412,"passed_time":0.3501882017,"remaining_time":0.4977251196},
{"learn":[0.3326973302],"iteration":413,"passed_time":0.3510507807,"remaining_time":0.496897965},
{"learn":[0.3324351324],"iteration":414,"passed_time":0.3518498631,"remaining_time":0.4959811324},
{"learn":[0.3319387682],"iteration":415,"passed_time":0.3527205257,"remaining_time":0.4951653535},
{"learn":[0.3314818558],"iteration":416,"passed_time":0.3535710644,"remaining_time":0.4943211764},
{"learn":[0.3312693054],"iteration":417,"passed_time":0.3544625589,"remaining_time":0.4935339935},
{"learn":[0.3306754655],"iteration":418,"passed_time":0.3553758022,"remaining_time":0.4927764704},
{"learn":[0.3304887251],"iteration":419,"passed_time":0.356206175,"remaining_time":0.4919037654},
{"learn":[0.3300994313],"iteration":420,"passed_time":0.3569791758,"remaining_time":0.4909523581},
{"learn":[0.3295534656],"iteration":421,"passed_time":0.357895085,"remaining_time":0.4901975334},
{"learn":[0.3291605448],"iteration":422,"passed_time":0.358664294,"remaining_time":0.4892418384},
{"learn":[0.3285919846],"iteration":423,"passed_time":0.3595570794,"remaining_time":0.4884549003},
{"learn":[0.3281549827],"iteration":424,"passed_time":0.3603604116,"remaining_time":0.4875464392},
{"learn":[0.3278709518],"iteration":425,"passed_time":0.3611577441,"remaining_time":0.4866303876},
{"learn":[0.3276722994],"iteration":426,"passed_time":0.3619787843,"remaining_time":0.4857467059},
{"learn":[0.3273397038],"iteration":427,"passed_time":0.3627622006,"remaining_time":0.4848130344},
{"learn":[0.3269651528],"iteration":428,"passed_time":0.3634652471,"remaining_time":0.4837730911},
{"learn":[0.3265908773],"iteration":429,"passed_time":0.3642138322,"remaining_time":0.4827950799},
{"learn":[0.3260625959],"iteration":430,"passed_time":0.3649694999,"remaining_time":0.4818274837},
{"learn":[0.3256573408],"iteration":431,"passed_time":0.3659685717,"remaining_time":0.4811808998},
{"learn":[0.3253288275],"iteration":432,"passed_time":0.3667573627,"remaining_time":0.4802573317},
{"learn":[0.3251716529],"iteration":433,"passed_time":0.3675826937,"remaining_time":0.4793820383},
{"learn":[0.3248285314],"iteration":434,"passed_time":0.368346237,"remaining_time":0.4784267216},
{"learn":[0.324341832],"iteration":435,"passed_time":0.3691550689,"remaining_time":0.4775308689},
{"learn":[0.3239841063],"iteration":436,"passed_time":0.3698997382,"remaining_time":0.4765527519},
{"learn":[0.3234284928],"iteration":437,"passed_time":0.3706778217,"remaining_time":0.4756185749},
{"learn":[0.3230960145],"iteration":438,"passed_time":0.3714929453,"remaining_time":0.4747324426},
{"learn":[0.3228289971],"iteration":439,"passed_time":0.3723924803,"remaining_time":0.4739540659},
{"learn":[0.3223910626],"iteration":440,"passed_time":0.3732523505,"remaining_time":0.4731248615},
{"learn":[0.3219379355],"iteration":441,"passed_time":0.37401231,"remaining_time":0.4721693868},
{"learn":[0.3217779655],"iteration":442,"passed_time":0.374762312,"remaining_time":0.4712022749},
{"learn":[0.3215112866],"iteration":443,"passed_time":0.375588101,"remaining_time":0.4703310454},
{"learn":[0.3208890637],"iteration":444,"passed_time":0.3762675238,"remaining_time":0.4692774735},
{"learn":[0.3206674801],"iteration":445,"passed_time":0.3770823974,"remaining_time":0.4683938299},
{"learn":[0.3204112537],"iteration":446,"passed_time":0.3779220196,"remaining_time":0.4675411115},
{"learn":[0.3201269637],"iteration":447,"passed_time":0.3787144774,"remaining_time":0.4666303382},
{"learn":[0.3198362421],"iteration":448,"passed_time":0.3794947268,"remaining_time":0.4657051102},
{"learn":[0.3192095329],"iteration":449,"passed_time":0.380242645,"remaining_time":0.4647410105},
{"learn":[0.3189128753],"iteration":450,"passed_time":0.3813133799,"remaining_time":0.4641708327},
{"learn":[0.3185429935],"iteration":451,"passed_time":0.3822767035,"remaining_time":0.4634682158},
{"learn":[0.3182753868],"iteration":452,"passed_time":0.3831194086,"remaining_time":0.4626188003},
{"learn":[0.3178834511],"iteration":453,"passed_time":0.3839171581,"remaining_time":0.4617153488},
{"learn":[0.3176964092],"iteration":454,"passed_time":0.3848283186,"remaining_time":0.4609482057},
{"learn":[0.3173473975],"iteration":455,"passed_time":0.3857083127,"remaining_time":0.4601432502},
{"learn":[0.3171786405],"iteration":456,"passed_time":0.387128237,"remaining_time":0.4599795026},
{"learn":[0.316790927],"iteration":457,"passed_time":0.3879216117,"remaining_time":0.4590688069},
{"learn":[0.3163870538],"iteration":458,"passed_time":0.3887860236,"remaining_time":0.4582423503},
{"learn":[0.3160851671],"iteration":459,"passed_time":0.3896519775,"remaining_time":0.4574175388},
{"learn":[0.315593347],"iteration":460,"passed_time":0.3903863543,"remaining_time":0.4564387093},
{"learn":[0.3151277205],"iteration":461,"passed_time":0.3913538448,"remaining_time":0.4557323993},
{"learn":[0.3149169786],"iteration":462,"passed_time":0.3921963409,"remaining_time":0.4548799893},
{"learn":[0.3147300064],"iteration":463,"passed_time":0.393037838,"remaining_time":0.4540264681},
{"learn":[0.3145555242],"iteration":464,"passed_time":0.3938811261,"remaining_time":0.4531750591},
{"learn":[0.3143199951],"iteration":465,"passed_time":0.3948063678,"remaining_time":0.4524175974},
{"learn":[0.3139935084],"iteration":466,"passed_time":0.3957319435,"remaining_time":0.4516597984},
{"learn":[0.3135726489],"iteration":467,"passed_time":0.3966740182,"remaining_time":0.4509200378},
{"learn":[0.3132766868],"iteration":468,"passed_time":0.3974903497,"remaining_time":0.4500370484},
{"learn":[0.3127834718],"iteration":469,"passed_time":0.3983129729,"remaining_time":0.4491614375},
{"learn":[0.312594873],"iteration":470,"passed_time":0.3991232217,"remaining_time":0.4482721535},
{"learn":[0.3124132052],"iteration":471,"passed_time":0.3999780922,"remaining_time":0.44743312},
{"learn":[0.3120226665],"iteration":472,"passed_time":0.4009458316,"remaining_time":0.4467197743},
{"learn":[0.3115012592],"iteration":473,"passed_time":0.4017569963,"remaining_time":0.4458316035},
{"learn":[0.3111219073],"iteration":474,"passed_time":0.4025927438,"remaining_time":0.4449709274},
{"learn":[0.3107454872],"iteration":475,"passed_time":0.4035869828,"remaining_time":0.4442848298},
{"learn":[0.3104613394],"iteration":476,"passed_time":0.405103068,"remaining_time":0.4441696113},
{"learn":[0.3101289152],"iteration":477,"passed_time":0.405928732,"remaining_time":0.4432945567},
{"learn":[0.3097930674],"iteration":478,"passed_time":0.4067858113,"remaining_time":0.4424538783},
{"learn":[0.30936701],"iteration":479,"passed_time":0.4075600621,"remaining_time":0.4415234006},
{"learn":[0.3091007645],"iteration":480,"passed_time":0.4083622273,"remaining_time":0.4406236923},
{"learn":[0.3087038108],"iteration":481,"passed_time":0.409193641,"remaining_time":0.4397558217},
{"learn":[0.308101505],"iteration":482,"passed_time":0.4099836819,"remaining_time":0.4388438169},
{"learn":[0.3078291765],"iteration":483,"passed_time":0.410733226,"remaining_time":0.4378891417},
{"learn":[0.3072694395],"iteration":484,"passed_time":0.411707924,"remaining_time":0.4371743935},
{"learn":[0.3069938673],"iteration":485,"passed_time":0.4125798775,"remaining_time":0.4363499116},
{"learn":[0.3067431806],"iteration":486,"passed_time":0.4134308322,"remaining_time":0.4355031148},
{"learn":[0.3064172254],"iteration":487,"passed_time":0.4141128378,"remaining_time":0.434479043},
{"learn":[0.3062193821],"iteration":488,"passed_time":0.415029206,"remaining_time":0.4337012766},
{"learn":[0.3058404294],"iteration":489,"passed_time":0.4159125759,"remaining_time":0.4328885994},
{"learn":[0.3054363749],"iteration":490,"passed_time":0.4167340321,"remaining_time":0.4320114508},
{"learn":[0.3050551513],"iteration":491,"passed_time":0.4175649459,"remaining_time":0.4311442937},
{"learn":[0.3047647542],"iteration":492,"passed_time":0.4184053181,"remaining_time":0.4302870107},
{"learn":[0.3045213397],"iteration":493,"passed_time":0.4194124724,"remaining_time":0.4296006296},
{"learn":[0.3041934909],"iteration":494,"passed_time":0.4203141743,"remaining_time":0.4288053698},
{"learn":[0.3040193499],"iteration":495,"passed_time":0.4211620452,"remaining_time":0.4279549814},
{"learn":[0.3036941723],"iteration":496,"passed_time":0.4220152077,"remaining_time":0.4271099587},
{"learn":[0.3034737019],"iteration":497,"passed_time":0.4227491266,"remaining_time":0.4261447019},
{"learn":[0.3032388536],"iteration":498,"passed_time":0.4236336204,"remaining_time":0.4253315508},
{"learn":[0.3024751124],"iteration":499,"passed_time":0.4245306146,"remaining_time":0.4245306146},
{"learn":[0.3020793604],"iteration":500,"passed_time":0.4253854441,"remaining_time":0.4236872986},
{"learn":[0.3015840218],"iteration":501,"passed_time":0.4261924851,"remaining_time":0.422796529},
{"learn":[0.3014106814],"iteration":502,"passed_time":0.4270806467,"remaining_time":0.4219862454},
{"learn":[0.3011515065],"iteration":503,"passed_time":0.4278004834,"remaining_time":0.4210099995},
{"learn":[0.3008360797],"iteration":504,"passed_time":0.4285525263,"remaining_time":0.4200663376},
{"learn":[0.3006630987],"iteration":505,"passed_time":0.4293981892,"remaining_time":0.4192148329},
{"learn":[0.3004230031],"iteration":506,"passed_time":0.4301918549,"remaining_time":0.4183127899},
{"learn":[0.3002248985],"iteration":507,"passed_time":0.4310077704,"remaining_time":0.4174327225},
{"learn":[0.2997902156],"iteration":508,"passed_time":0.431897432,"remaining_time":0.4166240454},
{"learn":[0.2993788868],"iteration":509,"passed_time":0.4327006802,"remaining_time":0.4157320261},
{"learn":[0.2991962081],"iteration":510,"passed_time":0.4334215168,"remaining_time":0.4147614906},
{"learn":[0.2989292638],"iteration":511,"passed_time":0.4343006369,"remaining_time":0.4139427946},
{"learn":[0.2986214763],"iteration":512,"passed_time":0.4350444723,"remaining_time":0.4129954347},
{"learn":[0.2982662506],"iteration":513,"passed_time":0.4357703086,"remaining_time":0.4120318482},
{"learn":[0.2980131639],"iteration":514,"passed_time":0.4365758497,"remaining_time":0.4111442468},
{"learn":[0.2977018585],"iteration":515,"passed_time":0.4372663129,"remaining_time":0.4101490222},
{"learn":[0.297419381],"iteration":516,"passed_time":0.4379739842,"remaining_time":0.4091710529},
{"learn":[0.2968681563],"iteration":517,"passed_time":0.4387743165,"remaining_time":0.4082803486},
{"learn":[0.2964964689],"iteration":518,"passed_time":0.4396893087,"remaining_time":0.4074962572},
{"learn":[0.2962753858],"iteration":519,"passed_time":0.4405616782,"remaining_time":0.4066723184},
{"learn":[0.2960917863],"iteration":520,"passed_time":0.4414697969,"remaining_time":0.4058810608},
{"learn":[0.2960252384],"iteration":521,"passed_time":0.4422606717,"remaining_time":0.4049819944},
{"learn":[0.2956720478],"iteration":522,"passed_time":0.4431842055,"remaining_time":0.4042043327},
{"learn":[0.2954113145],"iteration":523,"passed_time":0.4440444506,"remaining_time":0.4033686231},
{"learn":[0.2952496398],"iteration":524,"passed_time":0.444882281,"remaining_time":0.4025125399},
{"learn":[0.2950556748],"iteration":525,"passed_time":0.4457401103,"remaining_time":0.401674548},
{"learn":[0.2947848008],"iteration":526,"passed_time":0.4466668109,"remaining_time":0.4008982952},
{"learn":[0.2944771375],"iteration":527,"passed_time":0.4474660183,"remaining_time":0.4000075012},
{"learn":[0.2939039732],"iteration":528,"passed_time":0.4482996819,"remaining_time":0.3991477319},
{"learn":[0.293471002],"iteration":529,"passed_time":0.4491187632,"remaining_time":0.3982751296},
{"learn":[0.293383914],"iteration":530,"passed_time":0.4499191375,"remaining_time":0.3973862062},
{"learn":[0.2932369283],"iteration":531,"passed_time":0.4507149281,"remaining_time":0.3964935834},
{"learn":[0.2928547023],"iteration":532,"passed_time":0.4516724191,"remaining_time":0.3957430014},
{"learn":[0.2926795165],"iteration":533,"passed_time":0.4525610807,"remaining_time":0.3949315798},
{"learn":[0.2921634505],"iteration":534,"passed_time":0.4533683297,"remaining_time":0.394049109},
{"learn":[0.2917985113],"iteration":535,"passed_time":0.4542891136,"remaining_time":0.3932652029},
{"learn":[0.2914528996],"iteration":536,"passed_time":0.4552226049,"remaining_time":0.3924917431},
{"learn":[0.2911236317],"iteration":537,"passed_time":0.455989314,"remaining_time":0.3915744667},
{"learn":[0.2908490463],"iteration":538,"passed_time":0.4568420606,"remaining_time":0.3907313357},
{"learn":[0.2905927648],"iteration":539,"passed_time":0.4576848487,"remaining_time":0.3898796859},
{"learn":[0.2901864919],"iteration":540,"passed_time":0.4585962161,"remaining_time":0.3890862536},
{"learn":[0.2899492292],"iteration":541,"passed_time":0.4594016732,"remaining_time":0.3882028899},
{"learn":[0.2897007976],"iteration":542,"passed_time":0.460116968,"remaining_time":0.3872439308},
{"learn":[0.289376909],"iteration":543,"passed_time":0.4609404242,"remaining_time":0.386376532},
{"learn":[0.2891062066],"iteration":544,"passed_time":0.4617519219,"remaining_time":0.385499311},
{"learn":[0.2889078112],"iteration":545,"passed_time":0.462519423,"remaining_time":0.3845857473},
{"learn":[0.2885509484],"iteration":546,"passed_time":0.4633967103,"remaining_time":0.3837636376},
{"learn":[0.2881426346],"iteration":547,"passed_time":0.4642020013,"remaining_time":0.3828819427},
{"learn":[0.2877198541],"iteration":548,"passed_time":0.4650830794,"remaining_time":0.3820627847},
{"learn":[0.2876103159],"iteration":549,"passed_time":0.4659313262,"remaining_time":0.3812165396},
{"learn":[0.2873781313],"iteration":550,"passed_time":0.4667375332,"remaining_time":0.3803360298},
{"learn":[0.2870648779],"iteration":551,"passed_time":0.4674560789,"remaining_time":0.3793846438},
{"learn":[0.2868373722],"iteration":552,"passed_time":0.4682089968,"remaining_time":0.3784618835},
{"learn":[0.2864502574],"iteration":553,"passed_time":0.4691131146,"remaining_time":0.3776614605},
{"learn":[0.2862985088],"iteration":554,"passed_time":0.4698919061,"remaining_time":0.376760177},
{"learn":[0.2861859647],"iteration":555,"passed_time":0.4704629177,"remaining_time":0.3756934091},
{"learn":[0.2859481672],"iteration":556,"passed_time":0.4712832489,"remaining_time":0.3748267133},
{"learn":[0.2856868204],"iteration":557,"passed_time":0.4719666715,"remaining_time":0.3738517362},
{"learn":[0.2855140619],"iteration":558,"passed_time":0.472690216,"remaining_time":0.3729094548},
{"learn":[0.28524461],"iteration":559,"passed_time":0.4734256768,"remaining_time":0.3719773175},
{"learn":[0.2848741275],"iteration":560,"passed_time":0.4741372228,"remaining_time":0.3710271672},
{"learn":[0.2844974602],"iteration":561,"passed_time":0.4749282647,"remaining_time":0.3701398219},
{"learn":[0.2840561268],"iteration":562,"passed_time":0.4757155977,"remaining_time":0.36924994},
{"learn":[0.2837845976],"iteration":563,"passed_time":0.4766831712,"remaining_time":0.3684997564},
{"learn":[0.2835017682],"iteration":564,"passed_time":0.4776346204,"remaining_time":0.3677363892},
{"learn":[0.2831525272],"iteration":565,"passed_time":0.4784952836,"remaining_time":0.3669027439},
{"learn":[0.2829011523],"iteration":566,"passed_time":0.4793991104,"remaining_time":0.3661019661},
{"learn":[0.282429885],"iteration":567,"passed_time":0.480420765,"remaining_time":0.365390441},
{"learn":[0.2821103515],"iteration":568,"passed_time":0.4821028833,"remaining_time":0.3651781067},
{"learn":[0.2819164825],"iteration":569,"passed_time":0.4829306722,"remaining_time":0.3643161211},
{"learn":[0.281760206],"iteration":570,"passed_time":0.4837737523,"remaining_time":0.3634657438},
{"learn":[0.281631896],"iteration":571,"passed_time":0.4847879482,"remaining_time":0.3627434298},
{"learn":[0.2812038169],"iteration":572,"passed_time":0.4856662344,"remaining_time":0.3619188169},
{"learn":[0.2809977453],"iteration":573,"passed_time":0.4865333132,"remaining_time":0.3610856993},
{"learn":[0.2807291857],"iteration":574,"passed_time":0.4873328956,"remaining_time":0.360202575},
{"learn":[0.2805444184],"iteration":575,"passed_time":0.4881077293,"remaining_time":0.3593015229},
{"learn":[0.2803493392],"iteration":576,"passed_time":0.4889043958,"remaining_time":0.3584169141},
{"learn":[0.2799822984],"iteration":577,"passed_time":0.4897127277,"remaining_time":0.3575411265},
{"learn":[0.2796829828],"iteration":578,"passed_time":0.4905368088,"remaining_time":0.3566770233},
{"learn":[0.2793399515],"iteration":579,"passed_time":0.4913153093,"remaining_time":0.3557800516},
{"learn":[0.2789884357],"iteration":580,"passed_time":0.4921191005,"remaining_time":0.3549017265},
{"learn":[0.2789047844],"iteration":581,"passed_time":0.4931213391,"remaining_time":0.3541661851},
{"learn":[0.2785935913],"iteration":582,"passed_time":0.4940212491,"remaining_time":0.3533565367},
{"learn":[0.2783196235],"iteration":583,"passed_time":0.4948004986,"remaining_time":0.3524606291},
{"learn":[0.2780709208],"iteration":584,"passed_time":0.4954978364,"remaining_time":0.3515070122},
{"learn":[0.2776270683],"iteration":585,"passed_time":0.4963428754,"remaining_time":0.3506586184},
{"learn":[0.2773953361],"iteration":586,"passed_time":0.4973096159,"remaining_time":0.3498958626},
{"learn":[0.2771832784],"iteration":587,"passed_time":0.4980463686,"remaining_time":0.3489712651},
{"learn":[0.2769255725],"iteration":588,"passed_time":0.4989057398,"remaining_time":0.3481328677},
{"learn":[0.2767134283],"iteration":589,"passed_time":0.4999164779,"remaining_time":0.3473995864},
{"learn":[0.2763090126],"iteration":590,"passed_time":0.5007613079,"remaining_time":0.3465505498},
{"learn":[0.2760548632],"iteration":591,"passed_time":0.5015623072,"remaining_time":0.3456713198},
{"learn":[0.2758326597],"iteration":592,"passed_time":0.5024831331,"remaining_time":0.3448745956},
{"learn":[0.2753853205],"iteration":593,"passed_time":0.5032572999,"remaining_time":0.3439772117},
{"learn":[0.275062987],"iteration":594,"passed_time":0.5040338835,"remaining_time":0.3430818871},
{"learn":[0.2748381744],"iteration":595,"passed_time":0.5049168364,"remaining_time":0.3422590636},
{"learn":[0.2744514108],"iteration":596,"passed_time":0.5057612494,"remaining_time":0.3414100227},
{"learn":[0.2742215957],"iteration":597,"passed_time":0.5067100329,"remaining_time":0.3406311592},
{"learn":[0.2740086331],"iteration":598,"passed_time":0.5075731119,"remaining_time":0.3397943537},
{"learn":[0.2736522412],"iteration":599,"passed_time":0.5084814805,"remaining_time":0.3389876536},
{"learn":[0.2735557635],"iteration":600,"passed_time":0.5093635175,"remaining_time":0.3381631339},
{"learn":[0.2733360871],"iteration":601,"passed_time":0.5102018478,"remaining_time":0.3373095273},
{"learn":[0.2729000038],"iteration":602,"passed_time":0.5111430476,"remaining_time":0.336523698},
{"learn":[0.2726323161],"iteration":603,"passed_time":0.5119495876,"remaining_time":0.3356490674},
{"learn":[0.2723472345],"iteration":604,"passed_time":0.5127889599,"remaining_time":0.3347960978},
{"learn":[0.2718206118],"iteration":605,"passed_time":0.5135645436,"remaining_time":0.3339016999},
{"learn":[0.2716073564],"iteration":606,"passed_time":0.5143492517,"remaining_time":0.3330136012},
{"learn":[0.2712856343],"iteration":607,"passed_time":0.5151937477,"remaining_time":0.33216439},
{"learn":[0.271039693],"iteration":608,"passed_time":0.5166502951,"remaining_time":0.3317081533},
{"learn":[0.2708069509],"iteration":609,"passed_time":0.5173940475,"remaining_time":0.3307929156},
{"learn":[0.2704957632],"iteration":610,"passed_time":0.5181483823,"remaining_time":0.3298849766},
{"learn":[0.2703029879],"iteration":611,"passed_time":0.5189375902,"remaining_time":0.3289996487},
{"learn":[0.2700643005],"iteration":612,"passed_time":0.520460842,"remaining_time":0.328578052},
{"learn":[0.2699098277],"iteration":613,"passed_time":0.5212143849,"remaining_time":0.3276689781},
{"learn":[0.2695452035],"iteration":614,"passed_time":0.5219940103,"remaining_time":0.3267767382},
{"learn":[0.2692671092],"iteration":615,"passed_time":0.5228215912,"remaining_time":0.3259147582},
{"learn":[0.2690730197],"iteration":616,"passed_time":0.5237561664,"remaining_time":0.3251193059},
{"learn":[0.2688767489],"iteration":617,"passed_time":0.5245582906,"remaining_time":0.3242415324},
{"learn":[0.2687038838],"iteration":618,"passed_time":0.5253617058,"remaining_time":0.3233647979},
{"learn":[0.2685262317],"iteration":619,"passed_time":0.5260940418,"remaining_time":0.3224447353},
{"learn":[0.2682350457],"iteration":620,"passed_time":0.5269356639,"remaining_time":0.3215919753},
{"learn":[0.2680292139],"iteration":621,"passed_time":0.5276205434,"remaining_time":0.3206439959},
{"learn":[0.2677486798],"iteration":622,"passed_time":0.5284057096,"remaining_time":0.3197575482},
{"learn":[0.267378093],"iteration":623,"passed_time":0.5292467068,"remaining_time":0.3189050669},
{"learn":[0.267239728],"iteration":624,"passed_time":0.5300394555,"remaining_time":0.3180236733},
{"learn":[0.267162666],"iteration":625,"passed_time":0.5308598288,"remaining_time":0.317159067},
{"learn":[0.2668199962],"iteration":626,"passed_time":0.5316131637,"remaining_time":0.316254721},
{"learn":[0.2665474021],"iteration":627,"passed_time":0.5324114551,"remaining_time":0.3153774861},
{"learn":[0.2665048137],"iteration":628,"passed_time":0.5331868728,"remaining_time":0.3144870108},
{"learn":[0.2663594638],"iteration":629,"passed_time":0.5339173339,"remaining_time":0.3135704977},
{"learn":[0.2660781916],"iteration":630,"passed_time":0.5347016671,"remaining_time":0.3126860779},
{"learn":[0.2658251008],"iteration":631,"passed_time":0.5355801612,"remaining_time":0.3118568027},
{"learn":[0.265611455],"iteration":632,"passed_time":0.5363927849,"remaining_time":0.3109891818},
{"learn":[0.2654316261],"iteration":633,"passed_time":0.5372670303,"remaining_time":0.3101573077},
{"learn":[0.2652125904],"iteration":634,"passed_time":0.5381375259,"remaining_time":0.3093231448},
{"learn":[0.2649183747],"iteration":635,"passed_time":0.5389633149,"remaining_time":0.3084632809},
{"learn":[0.2646986083],"iteration":636,"passed_time":0.5397545228,"remaining_time":0.3075838175},
{"learn":[0.2645575681],"iteration":637,"passed_time":0.540576479,"remaining_time":0.3067220774},
{"learn":[0.2641807106],"iteration":638,"passed_time":0.5413555214,"remaining_time":0.3058362179},
{"learn":[0.2638826813],"iteration":639,"passed_time":0.5421723119,"remaining_time":0.3049719254},
{"learn":[0.2636191916],"iteration":640,"passed_time":0.5429225219,"remaining_time":0.304070492},
{"learn":[0.2632483346],"iteration":641,"passed_time":0.5438620549,"remaining_time":0.3032751022},
{"learn":[0.2630925269],"iteration":642,"passed_time":0.5446139318,"remaining_time":0.3023750757},
{"learn":[0.2628376121],"iteration":643,"passed_time":0.5455193835,"remaining_time":0.3015604046},
{"learn":[0.2625758877],"iteration":644,"passed_time":0.5463573389,"remaining_time":0.3007083028},
{"learn":[0.2621883047],"iteration":645,"passed_time":0.5472826645,"remaining_time":0.2999041227},
{"learn":[0.2620201365],"iteration":646,"passed_time":0.548231823,"remaining_time":0.2991125711},
{"learn":[0.2619154835],"iteration":647,"passed_time":0.5490524462,"remaining_time":0.2982507115},
{"learn":[0.2616234753],"iteration":648,"passed_time":0.549901401,"remaining_time":0.2974043016},
{"learn":[0.2614002378],"iteration":649,"passed_time":0.5506907749,"remaining_time":0.2965258019},
{"learn":[0.261238331],"iteration":650,"passed_time":0.5517123035,"remaining_time":0.2957720337},
{"learn":[0.2611232586],"iteration":651,"passed_time":0.5525684248,"remaining_time":0.2949291593},
{"learn":[0.2608972824],"iteration":652,"passed_time":0.553560706,"remaining_time":0.2941585987},
{"learn":[0.2605078263],"iteration":653,"passed_time":0.5543896618,"remaining_time":0.2933009526},
{"learn":[0.2603083504],"iteration":654,"passed_time":0.5552473241,"remaining_time":0.2924585142},
{"learn":[0.2601082188],"iteration":655,"passed_time":0.5563397239,"remaining_time":0.2917391235},
{"learn":[0.2599797296],"iteration":656,"passed_time":0.5573290461,"remaining_time":0.2909647836},
{"learn":[0.2598373576],"iteration":657,"passed_time":0.5582682881,"remaining_time":0.2901637607},
{"learn":[0.2594936349],"iteration":658,"passed_time":0.5591927388,"remaining_time":0.2893546645},
{"learn":[0.2592721168],"iteration":659,"passed_time":0.5600307351,"remaining_time":0.2885006817},
{"learn":[0.2590072184],"iteration":660,"passed_time":0.5608699814,"remaining_time":0.2876473883},
{"learn":[0.2585408571],"iteration":661,"passed_time":0.5617275607,"remaining_time":0.2868034978},
{"learn":[0.2584184228],"iteration":662,"passed_time":0.5626198882,"remaining_time":0.2859772282},
{"learn":[0.2581329553],"iteration":663,"passed_time":0.5633742229,"remaining_time":0.2850809321},
{"learn":[0.2578661331],"iteration":664,"passed_time":0.5641121836,"remaining_time":0.2841768143},
{"learn":[0.2577409523],"iteration":665,"passed_time":0.5649129329,"remaining_time":0.2833046841},
{"learn":[0.2574812819],"iteration":666,"passed_time":0.565718807,"remaining_time":0.2824353264},
{"learn":[0.2573035188],"iteration":667,"passed_time":0.5665088059,"remaining_time":0.2815582688},
{"learn":[0.2571719976],"iteration":668,"passed_time":0.5675887483,"remaining_time":0.2808249263},
{"learn":[0.2568812669],"iteration":669,"passed_time":0.568477201,"remaining_time":0.2799962333},
{"learn":[0.2566996497],"iteration":670,"passed_time":0.569359321,"remaining_time":0.2791642572},
{"learn":[0.2562530459],"iteration":671,"passed_time":0.5701810272,"remaining_time":0.2783026442},
{"learn":[0.2559246189],"iteration":672,"passed_time":0.571028857,"remaining_time":0.2774538428},
{"learn":[0.2557000456],"iteration":673,"passed_time":0.5718288144,"remaining_time":0.2765818894},
{"learn":[0.2554213362],"iteration":674,"passed_time":0.5726949772,"remaining_time":0.2757420261},
{"learn":[0.2552301904],"iteration":675,"passed_time":0.5736236357,"remaining_time":0.2749320384},
{"learn":[0.2551218589],"iteration":676,"passed_time":0.5749157748,"remaining_time":0.2742951186},
{"learn":[0.2548233619],"iteration":677,"passed_time":0.5756107378,"remaining_time":0.2733726513},
{"learn":[0.2545663356],"iteration":678,"passed_time":0.5764440274,"remaining_time":0.2725162486},
{"learn":[0.2543689816],"iteration":679,"passed_time":0.5772106945,"remaining_time":0.2716285621},
{"learn":[0.2540617592],"iteration":680,"passed_time":0.5781385611,"remaining_time":0.2708167415},
{"learn":[0.253734582],"iteration":681,"passed_time":0.5790181392,"remaining_time":0.2699820649},
{"learn":[0.2535774149],"iteration":682,"passed_time":0.5797595997,"remaining_time":0.2690831524},
{"learn":[0.2533732346],"iteration":683,"passed_time":0.5805900964,"remaining_time":0.268225834},
{"learn":[0.2529989764],"iteration":684,"passed_time":0.5813531808,"remaining_time":0.2673375941},
{"learn":[0.2525872906],"iteration":685,"passed_time":0.5821533471,"remaining_time":0.2664666924},
{"learn":[0.2522979152],"iteration":686,"passed_time":0.5830454656,"remaining_time":0.2656378904},
{"learn":[0.2521501252],"iteration":687,"passed_time":0.5838649219,"remaining_time":0.264775953},
{"learn":[0.2518162266],"iteration":688,"passed_time":0.5848681604,"remaining_time":0.2639970942},
{"learn":[0.2516510854],"iteration":689,"passed_time":0.5857376561,"remaining_time":0.2631574977},
{"learn":[0.2515331645],"iteration":690,"passed_time":0.5866233169,"remaining_time":0.2623250433},
{"learn":[0.2513356275],"iteration":691,"passed_time":0.587446398,"remaining_time":0.2614645818},
{"learn":[0.2509846908],"iteration":692,"passed_time":0.5882553549,"remaining_time":0.2605979711},
{"learn":[0.2506761818],"iteration":693,"passed_time":0.5891058516,"remaining_time":0.2597498423},
{"learn":[0.2505029203],"iteration":694,"passed_time":0.589885143,"remaining_time":0.2588704585},
{"learn":[0.2503418375],"iteration":695,"passed_time":0.5907502219,"remaining_time":0.2580288326},
{"learn":[0.2501799615],"iteration":696,"passed_time":0.5917099208,"remaining_time":0.2572282726},
{"learn":[0.2499220068],"iteration":697,"passed_time":0.5925592095,"remaining_time":0.2563794861},
{"learn":[0.2497416243],"iteration":698,"passed_time":0.5934916178,"remaining_time":0.2555664907},
{"learn":[0.2495525512],"iteration":699,"passed_time":0.5943266153,"remaining_time":0.2547114066},
{"learn":[0.2493991733],"iteration":700,"passed_time":0.595103241,"remaining_time":0.2538314822},
{"learn":[0.2491629201],"iteration":701,"passed_time":0.5959955274,"remaining_time":0.2530009504},
{"learn":[0.2490389544],"iteration":702,"passed_time":0.5969560592,"remaining_time":0.2521990748},
{"learn":[0.2486622805],"iteration":703,"passed_time":0.5977707238,"remaining_time":0.251335418},
{"learn":[0.2484744603],"iteration":704,"passed_time":0.5985398908,"remaining_time":0.2504528621},
{"learn":[0.2482280149],"iteration":705,"passed_time":0.5994867573,"remaining_time":0.249644627},
{"learn":[0.2480040285],"iteration":706,"passed_time":0.600336671,"remaining_time":0.2487958198},
{"learn":[0.2478252854],"iteration":707,"passed_time":0.6011507117,"remaining_time":0.2479322144},
{"learn":[0.2476367773],"iteration":708,"passed_time":0.6019641273,"remaining_time":0.2470684923},
{"learn":[0.2474259363],"iteration":709,"passed_time":0.6028012497,"remaining_time":0.2462145949},
{"learn":[0.247157087],"iteration":710,"passed_time":0.6036133724,"remaining_time":0.2453505832},
{"learn":[0.2469306736],"iteration":711,"passed_time":0.6044454941,"remaining_time":0.2444948066},
{"learn":[0.2467512229],"iteration":712,"passed_time":0.605215911,"remaining_time":0.2436142587},
{"learn":[0.2464109461],"iteration":713,"passed_time":0.6059043323,"remaining_time":0.2427011751},
{"learn":[0.2460869923],"iteration":714,"passed_time":0.6067133732,"remaining_time":0.2418367991},
{"learn":[0.2460073801],"iteration":715,"passed_time":0.607468083,"remaining_time":0.2409510273},
{"learn":[0.2458022082],"iteration":716,"passed_time":0.6083339948,"remaining_time":0.2401095126},
{"learn":[0.2455675233],"iteration":717,"passed_time":0.6091407848,"remaining_time":0.2392447094},
{"learn":[0.2453816103],"iteration":718,"passed_time":0.6099370764,"remaining_time":0.2383759645},
{"learn":[0.2451933061],"iteration":719,"passed_time":0.6107442834,"remaining_time":0.2375116658},
{"learn":[0.2450433134],"iteration":720,"passed_time":0.611633777,"remaining_time":0.2366793672},
{"learn":[0.2447346328],"iteration":721,"passed_time":0.6123598633,"remaining_time":0.2357839917},
{"learn":[0.2443682196],"iteration":722,"passed_time":0.613190903,"remaining_time":0.2349292948},
{"learn":[0.2441743522],"iteration":723,"passed_time":0.6139585281,"remaining_time":0.2340504886},
{"learn":[0.2439665237],"iteration":724,"passed_time":0.6148190232,"remaining_time":0.2332072157},
{"learn":[0.2437167212],"iteration":725,"passed_time":0.6157482657,"remaining_time":0.2323898413},
{"learn":[0.2434030818],"iteration":726,"passed_time":0.616492059,"remaining_time":0.2315025201},
{"learn":[0.2432736631],"iteration":727,"passed_time":0.6173603468,"remaining_time":0.2306621076},
{"learn":[0.2430456254],"iteration":728,"passed_time":0.6182133013,"remaining_time":0.2298159186},
{"learn":[0.2428771367],"iteration":729,"passed_time":0.6191314604,"remaining_time":0.2289938278},
{"learn":[0.2426293786],"iteration":730,"passed_time":0.61998354,"remaining_time":0.2281471577},
{"learn":[0.2424260873],"iteration":731,"passed_time":0.6207949137,"remaining_time":0.2272855695},
{"learn":[0.2422751822],"iteration":732,"passed_time":0.6216729919,"remaining_time":0.2264484159},
{"learn":[0.242129437],"iteration":733,"passed_time":0.6224341593,"remaining_time":0.2255687825},
{"learn":[0.2419479262],"iteration":734,"passed_time":0.6232276591,"remaining_time":0.2247011288},
{"learn":[0.2417534871],"iteration":735,"passed_time":0.6241264032,"remaining_time":0.2238714272},
{"learn":[0.2416802086],"iteration":736,"passed_time":0.6249508172,"remaining_time":0.2230150135},
{"learn":[0.2414331235],"iteration":737,"passed_time":0.6257457749,"remaining_time":0.222148229},
{"learn":[0.2412554845],"iteration":738,"passed_time":0.626549691,"remaining_time":0.2212848029},
{"learn":[0.2409806798],"iteration":739,"passed_time":0.6272950263,"remaining_time":0.2204009552},
{"learn":[0.2407801716],"iteration":740,"passed_time":0.6281089419,"remaining_time":0.219541452},
{"learn":[0.2405549632],"iteration":741,"passed_time":0.6289031076,"remaining_time":0.2186752045},
{"learn":[0.2403521437],"iteration":742,"passed_time":0.6296723166,"remaining_time":0.2178005187},
{"learn":[0.240146446],"iteration":743,"passed_time":0.6305112719,"remaining_time":0.2169501151},
{"learn":[0.2398779251],"iteration":744,"passed_time":0.6314023074,"remaining_time":0.2161175683},
{"learn":[0.2394838311],"iteration":745,"passed_time":0.6321641418,"remaining_time":0.215240874},
{"learn":[0.2390490312],"iteration":746,"passed_time":0.6329338088,"remaining_time":0.2143671401},
{"learn":[0.2389343859],"iteration":747,"passed_time":0.6337309333,"remaining_time":0.2135029347},
{"learn":[0.2388365602],"iteration":748,"passed_time":0.6346091785,"remaining_time":0.2126660932},
{"learn":[0.2384712375],"iteration":749,"passed_time":0.6353790954,"remaining_time":0.2117930318},
{"learn":[0.2382676267],"iteration":750,"passed_time":0.6362220085,"remaining_time":0.2109444476},
{"learn":[0.2379059986],"iteration":751,"passed_time":0.6369959673,"remaining_time":0.2100731381},
{"learn":[0.2375693215],"iteration":752,"passed_time":0.6377297202,"remaining_time":0.2091888989},
{"learn":[0.2373485788],"iteration":753,"passed_time":0.6385000541,"remaining_time":0.2083169938},
{"learn":[0.2371023536],"iteration":754,"passed_time":0.639272305,"remaining_time":0.2074459798},
{"learn":[0.2368782214],"iteration":755,"passed_time":0.6400292646,"remaining_time":0.2065702918},
{"learn":[0.2366761561],"iteration":756,"passed_time":0.6408085141,"remaining_time":0.2057020726},
{"learn":[0.2364146058],"iteration":757,"passed_time":0.6416017628,"remaining_time":0.2048385575},
{"learn":[0.236197238],"iteration":758,"passed_time":0.6424713415,"remaining_time":0.2039994642},
{"learn":[0.2359184072],"iteration":759,"passed_time":0.6434019999,"remaining_time":0.2031795789},
{"learn":[0.2357301921],"iteration":760,"passed_time":0.6444030305,"remaining_time":0.2023815037},
{"learn":[0.2354799209],"iteration":761,"passed_time":0.645219529,"remaining_time":0.2015252597},
{"learn":[0.2352980441],"iteration":762,"passed_time":0.6459823223,"remaining_time":0.2006524383},
{"learn":[0.2349882117],"iteration":763,"passed_time":0.6469515207,"remaining_time":0.1998436635},
{"learn":[0.2347691641],"iteration":764,"passed_time":0.6478638051,"remaining_time":0.1990169859},
{"learn":[0.2344993217],"iteration":765,"passed_time":0.6487695068,"remaining_time":0.1981880739},
{"learn":[0.2342046675],"iteration":766,"passed_time":0.6495366319,"remaining_time":0.1973168647},
{"learn":[0.2340121996],"iteration":767,"passed_time":0.6509346414,"remaining_time":0.1966365063},
{"learn":[0.2337820718],"iteration":768,"passed_time":0.6516851014,"remaining_time":0.1957597639},
{"learn":[0.2334942303],"iteration":769,"passed_time":0.6524284368,"remaining_time":0.1948812214},
{"learn":[0.233368244],"iteration":770,"passed_time":0.6533666778,"remaining_time":0.1940609199},
{"learn":[0.2331267162],"iteration":771,"passed_time":0.6542250071,"remaining_time":0.1932167119},
{"learn":[0.2327546215],"iteration":772,"passed_time":0.6550195897,"remaining_time":0.1923537476},
{"learn":[0.2324983511],"iteration":773,"passed_time":0.6557514257,"remaining_time":0.1914726385},
{"learn":[0.2320712436],"iteration":774,"passed_time":0.656477053,"remaining_time":0.1905901122},
{"learn":[0.2317440416],"iteration":775,"passed_time":0.6573071338,"remaining_time":0.1897381417},
{"learn":[0.2315922825],"iteration":776,"passed_time":0.6580369289,"remaining_time":0.1888574455},
{"learn":[0.2314422802],"iteration":777,"passed_time":0.6587757645,"remaining_time":0.1879797169},
{"learn":[0.2310528673],"iteration":778,"passed_time":0.6596212615,"remaining_time":0.1871326043},
{"learn":[0.2308307726],"iteration":779,"passed_time":0.6603665967,"remaining_time":0.1862572452},
{"learn":[0.2307105783],"iteration":780,"passed_time":0.6612498827,"remaining_time":0.1854209018},
{"learn":[0.2303924724],"iteration":781,"passed_time":0.6621488768,"remaining_time":0.1845888173},
{"learn":[0.2301418356],"iteration":782,"passed_time":0.6630513287,"remaining_time":0.1837575202},
{"learn":[0.2299623674],"iteration":783,"passed_time":0.6639489468,"remaining_time":0.1829247098},
{"learn":[0.2297935063],"iteration":784,"passed_time":0.6648206924,"remaining_time":0.1820846482},
{"learn":[0.2295905172],"iteration":785,"passed_time":0.6658120565,"remaining_time":0.1812770739},
{"learn":[0.2294383301],"iteration":786,"passed_time":0.6667890455,"remaining_time":0.1804651419},
{"learn":[0.2292543586],"iteration":787,"passed_time":0.6675822122,"remaining_time":0.1796033363},
{"learn":[0.2291216264],"iteration":788,"passed_time":0.6685854507,"remaining_time":0.1787978835},
{"learn":[0.2290020874],"iteration":789,"passed_time":0.669424989,"remaining_time":0.1779484148},
{"learn":[0.228861224],"iteration":790,"passed_time":0.6702237794,"remaining_time":0.1770882047},
{"learn":[0.2286799516],"iteration":791,"passed_time":0.670999946,"remaining_time":0.176222208},
{"learn":[0.2283939817],"iteration":792,"passed_time":0.6718588583,"remaining_time":0.1753780374},
{"learn":[0.2283019306],"iteration":793,"passed_time":0.6726091523,"remaining_time":0.1745056491},
{"learn":[0.2280655961],"iteration":794,"passed_time":0.6734923552,"remaining_time":0.17366784},
{"learn":[0.228004375],"iteration":795,"passed_time":0.6743551842,"remaining_time":0.1728246955},
{"learn":[0.2278373265],"iteration":796,"passed_time":0.6751581414,"remaining_time":0.1719662518},
{"learn":[0.2275576116],"iteration":797,"passed_time":0.675916934,"remaining_time":0.1710967677},
{"learn":[0.2272416664],"iteration":798,"passed_time":0.6767727214,"remaining_time":0.1702519612},
{"learn":[0.2270426856],"iteration":799,"passed_time":0.6774903501,"remaining_time":0.1693725875},
{"learn":[0.2268734096],"iteration":800,"passed_time":0.6786774119,"remaining_time":0.1686102434},
{"learn":[0.2266761959],"iteration":801,"passed_time":0.6796175698,"remaining_time":0.1677858838},
{"learn":[0.2265811953],"iteration":802,"passed_time":0.6803981952,"remaining_time":0.1669220977},
{"learn":[0.2263986866],"iteration":803,"passed_time":0.6811659462,"remaining_time":0.1660553799},
{"learn":[0.2262660841],"iteration":804,"passed_time":0.6820041936,"remaining_time":0.1652059848},
{"learn":[0.2258865171],"iteration":805,"passed_time":0.6831832967,"remaining_time":0.1644386595},
{"learn":[0.2257264232],"iteration":806,"passed_time":0.6839382985,"remaining_time":0.1635688867},
{"learn":[0.2255106863],"iteration":807,"passed_time":0.6848208354,"remaining_time":0.1627297035},
{"learn":[0.2252554152],"iteration":808,"passed_time":0.6857898258,"remaining_time":0.1619108241},
{"learn":[0.2250562878],"iteration":809,"passed_time":0.6866141569,"remaining_time":0.1610576417},
{"learn":[0.2250157346],"iteration":810,"passed_time":0.6870113857,"remaining_time":0.1601049962},
{"learn":[0.2248546247],"iteration":811,"passed_time":0.6877697203,"remaining_time":0.1592373244},
{"learn":[0.2246782243],"iteration":812,"passed_time":0.6885666358,"remaining_time":0.1583787957},
{"learn":[0.2243861997],"iteration":813,"passed_time":0.6893096382,"remaining_time":0.1575080992},
{"learn":[0.2241040361],"iteration":814,"passed_time":0.6901171782,"remaining_time":0.1566523656},
{"learn":[0.2239668288],"iteration":815,"passed_time":0.6908571797,"remaining_time":0.1557815209},
{"learn":[0.2238054847],"iteration":816,"passed_time":0.6917205497,"remaining_time":0.1549386299},
{"learn":[0.2236606496],"iteration":817,"passed_time":0.6926630405,"remaining_time":0.1541132926},
{"learn":[0.2235817267],"iteration":818,"passed_time":0.6936030744,"remaining_time":0.1532871263},
{"learn":[0.2234552174],"iteration":819,"passed_time":0.6944411547,"remaining_time":0.1524383023},
{"learn":[0.2233245788],"iteration":820,"passed_time":0.69528111,"remaining_time":0.1515899131},
{"learn":[0.2232125135],"iteration":821,"passed_time":0.696105607,"remaining_time":0.1507381971},
{"learn":[0.2229436092],"iteration":822,"passed_time":0.6970863458,"remaining_time":0.1499201497},
{"learn":[0.2228308474],"iteration":823,"passed_time":0.6980033389,"remaining_time":0.1490880918},
{"learn":[0.2226323753],"iteration":824,"passed_time":0.6988374614,"remaining_time":0.1482382494},
{"learn":[0.2223935492],"iteration":825,"passed_time":0.6995979209,"remaining_time":0.1473729276},
{"learn":[0.2222331251],"iteration":826,"passed_time":0.7003897117,"remaining_time":0.1465144137},
{"learn":[0.2220777798],"iteration":827,"passed_time":0.7011951268,"remaining_time":0.1456588911},
{"learn":[0.2219529646],"iteration":828,"passed_time":0.7020454565,"remaining_time":0.144812754},
{"learn":[0.2216404119],"iteration":829,"passed_time":0.7029318672,"remaining_time":0.1439739969},
{"learn":[0.2214560463],"iteration":830,"passed_time":0.7037202422,"remaining_time":0.1431151876},
{"learn":[0.2212681312],"iteration":831,"passed_time":0.7045075752,"remaining_time":0.1422563373},
{"learn":[0.2210693723],"iteration":832,"passed_time":0.7052951583,"remaining_time":0.1413977088},
{"learn":[0.2208325591],"iteration":833,"passed_time":0.7061305297,"remaining_time":0.1405487625},
{"learn":[0.2207041168],"iteration":834,"passed_time":0.7070015673,"remaining_time":0.1397068965},
{"learn":[0.2204144538],"iteration":835,"passed_time":0.7078344819,"remaining_time":0.1388574821},
{"learn":[0.2200619276],"iteration":836,"passed_time":0.7087404337,"remaining_time":0.1380223306},
{"learn":[0.2200117744],"iteration":837,"passed_time":0.7096403857,"remaining_time":0.1371858502},
{"learn":[0.2199637679],"iteration":838,"passed_time":0.7105873772,"remaining_time":0.1363582452},
{"learn":[0.2198379107],"iteration":839,"passed_time":0.711454331,"remaining_time":0.1355151107},
{"learn":[0.2193728664],"iteration":840,"passed_time":0.7122647048,"remaining_time":0.1346612224},
{"learn":[0.2191844],"iteration":841,"passed_time":0.7131501166,"remaining_time":0.1338215183},
{"learn":[0.2191132462],"iteration":842,"passed_time":0.7139292421,"remaining_time":0.132961911},
{"learn":[0.2188382423],"iteration":843,"passed_time":0.7148607335,"remaining_time":0.1321306569},
{"learn":[0.2185863277],"iteration":844,"passed_time":0.7157782676,"remaining_time":0.1312966053},
{"learn":[0.2183307304],"iteration":845,"passed_time":0.7165327684,"remaining_time":0.1304326789},
{"learn":[0.2182081982],"iteration":846,"passed_time":0.7177226219,"remaining_time":0.1296476519},
{"learn":[0.2179519565],"iteration":847,"passed_time":0.7188127308,"remaining_time":0.1288437914},
{"learn":[0.217672036],"iteration":848,"passed_time":0.7197653471,"remaining_time":0.1280148026},
{"learn":[0.2174165081],"iteration":849,"passed_time":0.7207922503,"remaining_time":0.1271986324},
{"learn":[0.2172483412],"iteration":850,"passed_time":0.7216672867,"remaining_time":0.1263553769},
{"learn":[0.2170654291],"iteration":851,"passed_time":0.7225007003,"remaining_time":0.1255048165},
{"learn":[0.2169203613],"iteration":852,"passed_time":0.7232019959,"remaining_time":0.124631528},
{"learn":[0.216780278],"iteration":853,"passed_time":0.7239485811,"remaining_time":0.1237663851},
{"learn":[0.2165980842],"iteration":854,"passed_time":0.7246666679,"remaining_time":0.1228966864},
{"learn":[0.2162805098],"iteration":855,"passed_time":0.7254362938,"remaining_time":0.122036012},
{"learn":[0.2162029861],"iteration":856,"passed_time":0.7262750411,"remaining_time":0.1211870839},
{"learn":[0.2160231324],"iteration":857,"passed_time":0.7271113716,"remaining_time":0.1203377794},
{"learn":[0.2159097399],"iteration":858,"passed_time":0.727890746,"remaining_time":0.1194791562},
{"learn":[0.2158644237],"iteration":859,"passed_time":0.7286429969,"remaining_time":0.1186163018},
{"learn":[0.2157223689],"iteration":860,"passed_time":0.729411123,"remaining_time":0.1177562672},
{"learn":[0.2156080156],"iteration":861,"passed_time":0.7301767902,"remaining_time":0.1168960523},
{"learn":[0.2153662288],"iteration":862,"passed_time":0.7309241674,"remaining_time":0.1160331529},
{"learn":[0.2152212982],"iteration":863,"passed_time":0.7317297084,"remaining_time":0.1151796763},
{"learn":[0.2150664285],"iteration":864,"passed_time":0.7324277132,"remaining_time":0.1143095275},
{"learn":[0.2148123501],"iteration":865,"passed_time":0.7332365041,"remaining_time":0.1134569187},
{"learn":[0.2147020722],"iteration":866,"passed_time":0.73398963,"remaining_time":0.1125958717},
{"learn":[0.214418299],"iteration":867,"passed_time":0.7347816708,"remaining_time":0.1117409914},
{"learn":[0.2141929086],"iteration":868,"passed_time":0.7357076634,"remaining_time":0.1109064487},
{"learn":[0.2140764392],"iteration":869,"passed_time":0.7364798723,"remaining_time":0.1100487165},
{"learn":[0.2137518959],"iteration":870,"passed_time":0.7373541177,"remaining_time":0.109206293},
{"learn":[0.2135473676],"iteration":871,"passed_time":0.7381439506,"remaining_time":0.1083514056},
{"learn":[0.2133598259],"iteration":872,"passed_time":0.7389631569,"remaining_time":0.1075009404},
{"learn":[0.2130993405],"iteration":873,"passed_time":0.7399627287,"remaining_time":0.106676549},
{"learn":[0.21298025],"iteration":874,"passed_time":0.7409044705,"remaining_time":0.1058434958},
{"learn":[0.2128378295],"iteration":875,"passed_time":0.7423263107,"remaining_time":0.1050781536},
{"learn":[0.2126281252],"iteration":876,"passed_time":0.7432597189,"remaining_time":0.1042428112},
{"learn":[0.2124114698],"iteration":877,"passed_time":0.7440972153,"remaining_time":0.1033939183},
{"learn":[0.21227058],"iteration":878,"passed_time":0.7448100523,"remaining_time":0.1025278912},
{"learn":[0.2121697928],"iteration":879,"passed_time":0.745715837,"remaining_time":0.1016885232},
{"learn":[0.2119698459],"iteration":880,"passed_time":0.7465538344,"remaining_time":0.1008398482},
{"learn":[0.2117954694],"iteration":881,"passed_time":0.7474274128,"remaining_time":0.09999595773},
{"learn":[0.2115134146],"iteration":882,"passed_time":0.7482299541,"remaining_time":0.09914258734},
{"learn":[0.2113627383],"iteration":883,"passed_time":0.7490884083,"remaining_time":0.09829666896},
{"learn":[0.2111576438],"iteration":884,"passed_time":0.7499529872,"remaining_time":0.09745151811},
{"learn":[0.2109906127],"iteration":885,"passed_time":0.751440199,"remaining_time":0.09668643644},
{"learn":[0.2107670264],"iteration":886,"passed_time":0.7523663576,"remaining_time":0.09584825074},
{"learn":[0.2106244097],"iteration":887,"passed_time":0.7535202121,"remaining_time":0.09503858531},
{"learn":[0.2104803063],"iteration":888,"passed_time":0.7543086281,"remaining_time":0.09418251712},
{"learn":[0.2103785574],"iteration":889,"passed_time":0.7551432926,"remaining_time":0.09333231706},
{"learn":[0.2102473991],"iteration":890,"passed_time":0.7559702075,"remaining_time":0.09248120384},
{"learn":[0.2100884896],"iteration":891,"passed_time":0.7568962002,"remaining_time":0.09164214083},
{"learn":[0.209968762],"iteration":892,"passed_time":0.7576847002,"remaining_time":0.09078640864},
{"learn":[0.2098029947],"iteration":893,"passed_time":0.7585345299,"remaining_time":0.08993809862},
{"learn":[0.2095524714],"iteration":894,"passed_time":0.7593146133,"remaining_time":0.08908160268},
{"learn":[0.2093780499],"iteration":895,"passed_time":0.7601516937,"remaining_time":0.08823189302},
{"learn":[0.2092623592],"iteration":896,"passed_time":0.7609413186,"remaining_time":0.08737676234},
{"learn":[0.209204821],"iteration":897,"passed_time":0.7618592697,"remaining_time":0.08653635357},
{"learn":[0.2090901718],"iteration":898,"passed_time":0.7627134322,"remaining_time":0.08568860584},
{"learn":[0.2088301322],"iteration":899,"passed_time":0.7634890988,"remaining_time":0.08483212209},
{"learn":[0.2086157904],"iteration":900,"passed_time":0.7643548027,"remaining_time":0.08398571084},
{"learn":[0.2082788424],"iteration":901,"passed_time":0.7651946329,"remaining_time":0.08313644571},
{"learn":[0.2079901363],"iteration":902,"passed_time":0.7659932984,"remaining_time":0.08228277956},
{"learn":[0.2077771737],"iteration":903,"passed_time":0.7668345035,"remaining_time":0.08143375259},
{"learn":[0.2076541742],"iteration":904,"passed_time":0.7676229615,"remaining_time":0.0805792059},
{"learn":[0.2073653891],"iteration":905,"passed_time":0.7684617088,"remaining_time":0.07973002277},
{"learn":[0.2073046327],"iteration":906,"passed_time":0.7692901237,"remaining_time":0.0788798032},
{"learn":[0.2070731492],"iteration":907,"passed_time":0.7700919139,"remaining_time":0.07802693401},
{"learn":[0.2069097036],"iteration":908,"passed_time":0.7707914186,"remaining_time":0.0771639374},
{"learn":[0.2067020978],"iteration":909,"passed_time":0.7717541173,"remaining_time":0.07632733029},
{"learn":[0.2064947528],"iteration":910,"passed_time":0.7725634082,"remaining_time":0.0754754592},
{"learn":[0.2062766714],"iteration":911,"passed_time":0.7734794424,"remaining_time":0.07463398128},
{"learn":[0.2061144328],"iteration":912,"passed_time":0.7742904412,"remaining_time":0.0737823312},
{"learn":[0.2058553321],"iteration":913,"passed_time":0.7750648169,"remaining_time":0.07292732413},
{"learn":[0.2057146533],"iteration":914,"passed_time":0.7758645663,"remaining_time":0.07207485042},
{"learn":[0.2054725754],"iteration":915,"passed_time":0.7765696537,"remaining_time":0.07121381104},
{"learn":[0.2052956016],"iteration":916,"passed_time":0.7775874324,"remaining_time":0.07038141428},
{"learn":[0.205194946],"iteration":917,"passed_time":0.7784108886,"remaining_time":0.06953125584},
{"learn":[0.2051184766],"iteration":918,"passed_time":0.7791704731,"remaining_time":0.06867552592},
{"learn":[0.2048576495],"iteration":919,"passed_time":0.7801046313,"remaining_time":0.06783518533},
{"learn":[0.2046458902],"iteration":920,"passed_time":0.7809628776,"remaining_time":0.06698812956},
{"learn":[0.204553975],"iteration":921,"passed_time":0.7818120403,"remaining_time":0.06614028107},
{"learn":[0.2043729125],"iteration":922,"passed_time":0.7827659895,"remaining_time":0.06530117138},
{"learn":[0.2042960942],"iteration":923,"passed_time":0.7835844038,"remaining_time":0.06445066525},
{"learn":[0.2040353274],"iteration":924,"passed_time":0.7844484828,"remaining_time":0.06360393104},
{"learn":[0.203749877],"iteration":925,"passed_time":0.785363976,"remaining_time":0.06276126806},
{"learn":[0.2034805872],"iteration":926,"passed_time":0.7864223786,"remaining_time":0.06192970187},
{"learn":[0.2033487329],"iteration":927,"passed_time":0.7874056182,"remaining_time":0.0610918152},
{"learn":[0.2032299444],"iteration":928,"passed_time":0.7884137725,"remaining_time":0.06025551975},
{"learn":[0.2030214602],"iteration":929,"passed_time":0.7892350207,"remaining_time":0.0594047865},
{"learn":[0.2029227957],"iteration":930,"passed_time":0.7900708511,"remaining_time":0.05855519735},
{"learn":[0.2027942514],"iteration":931,"passed_time":0.7908601001,"remaining_time":0.05770223906},
{"learn":[0.2025458954],"iteration":932,"passed_time":0.7916383506,"remaining_time":0.05684862754},
{"learn":[0.2024848976],"iteration":933,"passed_time":0.7925184287,"remaining_time":0.05600237291},
{"learn":[0.202399512],"iteration":934,"passed_time":0.793338135,"remaining_time":0.05515184896},
{"learn":[0.2022349087],"iteration":935,"passed_time":0.7942120054,"remaining_time":0.05430509439},
{"learn":[0.2019978333],"iteration":936,"passed_time":0.7950190034,"remaining_time":0.05345378572},
{"learn":[0.2018332498],"iteration":937,"passed_time":0.7958874162,"remaining_time":0.05260663092},
{"learn":[0.2016291542],"iteration":938,"passed_time":0.7966685825,"remaining_time":0.05175376308},
{"learn":[0.201448777],"iteration":939,"passed_time":0.7975364523,"remaining_time":0.05090658206},
{"learn":[0.2012629727],"iteration":940,"passed_time":0.79832916,"remaining_time":0.05005464446},
{"learn":[0.2011223164],"iteration":941,"passed_time":0.7991380339,"remaining_time":0.04920382799},
{"learn":[0.2009260244],"iteration":942,"passed_time":0.7999796981,"remaining_time":0.04835508249},
{"learn":[0.2007117397],"iteration":943,"passed_time":0.8008639419,"remaining_time":0.04750887791},
{"learn":[0.2005151712],"iteration":944,"passed_time":0.8017747684,"remaining_time":0.04666413996},
{"learn":[0.2002800819],"iteration":945,"passed_time":0.8026696787,"remaining_time":0.04581835375},
{"learn":[0.200013094],"iteration":946,"passed_time":0.8035408403,"remaining_time":0.04497113467},
{"learn":[0.1998860275],"iteration":947,"passed_time":0.8044542506,"remaining_time":0.04412618252},
{"learn":[0.1997717076],"iteration":948,"passed_time":0.8054443228,"remaining_time":0.04328520597},
{"learn":[0.1997596326],"iteration":949,"passed_time":0.8059636701,"remaining_time":0.04241914053},
{"learn":[0.1997227119],"iteration":950,"passed_time":0.8067300883,"remaining_time":0.04156653452},
{"learn":[0.1996049431],"iteration":951,"passed_time":0.8074583825,"remaining_time":0.04071218735},
{"learn":[0.1995281526],"iteration":952,"passed_time":0.8083103371,"remaining_time":0.0398642034},
{"learn":[0.1993097592],"iteration":953,"passed_time":0.8091423757,"remaining_time":0.03901525082},
{"learn":[0.1990541604],"iteration":954,"passed_time":0.809849671,"remaining_time":0.0381604557},
{"learn":[0.1987943427],"iteration":955,"passed_time":0.8106525032,"remaining_time":0.03731036626},
{"learn":[0.1986532598],"iteration":956,"passed_time":0.8115299145,"remaining_time":0.03646372657},
{"learn":[0.198493364],"iteration":957,"passed_time":0.8123930345,"remaining_time":0.03561639608},
{"learn":[0.1983896063],"iteration":958,"passed_time":0.8131761597,"remaining_time":0.03476561267},
{"learn":[0.1982939059],"iteration":959,"passed_time":0.8139169123,"remaining_time":0.03391320468},
{"learn":[0.1981143889],"iteration":960,"passed_time":0.8147435762,"remaining_time":0.03306451558},
{"learn":[0.1980449587],"iteration":961,"passed_time":0.8155011608,"remaining_time":0.03221314357},
{"learn":[0.1978589732],"iteration":962,"passed_time":0.8164275705,"remaining_time":0.03136845286},
{"learn":[0.1974643068],"iteration":963,"passed_time":0.8172442349,"remaining_time":0.03051949425},
{"learn":[0.1972407806],"iteration":964,"passed_time":0.8181180214,"remaining_time":0.02967267435},
{"learn":[0.1972168161],"iteration":965,"passed_time":0.8186534098,"remaining_time":0.02881388813},
{"learn":[0.1971307202],"iteration":966,"passed_time":0.8193685807,"remaining_time":0.02796190606},
{"learn":[0.1969823966],"iteration":967,"passed_time":0.8202341176,"remaining_time":0.02711517744},
{"learn":[0.1969458488],"iteration":968,"passed_time":0.8208625001,"remaining_time":0.02626082302},
{"learn":[0.1968810321],"iteration":969,"passed_time":0.8216402507,"remaining_time":0.02541155414},
{"learn":[0.1966996466],"iteration":970,"passed_time":0.822553493,"remaining_time":0.02456647919},
{"learn":[0.1964543707],"iteration":971,"passed_time":0.8233817408,"remaining_time":0.02371881558},
{"learn":[0.1964252226],"iteration":972,"passed_time":0.8241039104,"remaining_time":0.02286824828},
{"learn":[0.1962004978],"iteration":973,"passed_time":0.8248336215,"remaining_time":0.02201814595},
{"learn":[0.196068935],"iteration":974,"passed_time":0.8255703322,"remaining_time":0.02116847006},
{"learn":[0.1959364316],"iteration":975,"passed_time":0.8263104598,"remaining_time":0.02031910967},
{"learn":[0.1958383859],"iteration":976,"passed_time":0.8270029228,"remaining_time":0.01946885079},
{"learn":[0.1956220646],"iteration":977,"passed_time":0.8278108388,"remaining_time":0.01862151171},
{"learn":[0.1954377969],"iteration":978,"passed_time":0.8285959629,"remaining_time":0.01777376427},
{"learn":[0.1954189416],"iteration":979,"passed_time":0.8292033056,"remaining_time":0.01692251644},
{"learn":[0.1952044446],"iteration":980,"passed_time":0.8300659676,"remaining_time":0.01607671089},
{"learn":[0.1950696083],"iteration":981,"passed_time":0.8309560032,"remaining_time":0.01523137277},
{"learn":[0.1949112393],"iteration":982,"passed_time":0.8318647877,"remaining_time":0.01438626795},
{"learn":[0.1947637502],"iteration":983,"passed_time":0.8327476157,"remaining_time":0.01354061164},
{"learn":[0.1945952099],"iteration":984,"passed_time":0.8335539057,"remaining_time":0.0126937143},
{"learn":[0.1945153602],"iteration":985,"passed_time":0.8343752369,"remaining_time":0.0118471129},
{"learn":[0.1942279488],"iteration":986,"passed_time":0.835162695,"remaining_time":0.01100011655},
{"learn":[0.1940431415],"iteration":987,"passed_time":0.8360313987,"remaining_time":0.01015422751},
{"learn":[0.1940087117],"iteration":988,"passed_time":0.8368824783,"remaining_time":0.009308096321},
{"learn":[0.1939021362],"iteration":989,"passed_time":0.8376625207,"remaining_time":0.008461237583},
{"learn":[0.1937379953],"iteration":990,"passed_time":0.8387138817,"remaining_time":0.007616977735},
{"learn":[0.1936477147],"iteration":991,"passed_time":0.8397305365,"remaining_time":0.006772020456},
{"learn":[0.1934212797],"iteration":992,"passed_time":0.8405733666,"remaining_time":0.00592549201},
{"learn":[0.1931506122],"iteration":993,"passed_time":0.8413901981,"remaining_time":0.005078814073},
{"learn":[0.1928951866],"iteration":994,"passed_time":0.8422795667,"remaining_time":0.004232560637},
{"learn":[0.1928534358],"iteration":995,"passed_time":0.8431009389,"remaining_time":0.003385947546},
{"learn":[0.1927039108],"iteration":996,"passed_time":0.8439337695,"remaining_time":0.002539419567},
{"learn":[0.1924233454],"iteration":997,"passed_time":0.8447644752,"remaining_time":0.00169291478},
{"learn":[0.1921477868],"iteration":998,"passed_time":0.8455798898,"remaining_time":0.0008464263161},
{"learn":[0.1920961763],"iteration":999,"passed_time":0.8465051735,"remaining_time":0}
]}